{
  "results": [
    {
      "id": 1,
      "ml_score": 279.43
    },
    {
      "id": 2,
      "ml_score": 327.12
    },
    {
      "id": 3,
      "ml_score": 294.49
    },
    {
      "id": 4,
      "ml_score": 210.89
    },
    {
      "id": 5,
      "ml_score": 248.56
    },
    {
      "id": 6,
      "ml_score": 248.58
    },
    {
      "id": 7,
      "ml_score": 216.28
    },
    {
      "id": 8,
      "ml_score": 271.92
    },
    {
      "id": 9,
      "ml_score": 199.59
    },
    {
      "id": 10,
      "ml_score": 187.42
    },
    {
      "id": 11,
      "ml_score": 193.93
    },
    {
      "id": 12,
      "ml_score": 155.68
    },
    {
      "id": 13,
      "ml_score": 203
    },
    {
      "id": 14,
      "ml_score": 253.56
    },
    {
      "id": 15,
      "ml_score": 276.83
    },
    {
      "id": 16,
      "ml_score": 289.71
    },
    {
      "id": 17,
      "ml_score": 206.87
    },
    {
      "id": 18,
      "ml_score": 241.58
    },
    {
      "id": 19,
      "ml_score": 235.5
    },
    {
      "id": 20,
      "ml_score": 241.62
    },
    {
      "id": 21,
      "ml_score": 195.95
    },
    {
      "id": 22,
      "ml_score": 188.14
    },
    {
      "id": 23,
      "ml_score": 191.74
    },
    {
      "id": 24,
      "ml_score": 204.85
    },
    {
      "id": 25,
      "ml_score": 218.36
    },
    {
      "id": 26,
      "ml_score": 260.71
    },
    {
      "id": 27,
      "ml_score": 254.47
    },
    {
      "id": 28,
      "ml_score": 235.59
    },
    {
      "id": 29,
      "ml_score": 281.63
    },
    {
      "id": 30,
      "ml_score": 201.24
    },
    {
      "id": 31,
      "ml_score": 198.95
    },
    {
      "id": 32,
      "ml_score": 190.54
    },
    {
      "id": 33,
      "ml_score": 200.88
    },
    {
      "id": 34,
      "ml_score": 194.2
    },
    {
      "id": 35,
      "ml_score": 297.02
    },
    {
      "id": 36,
      "ml_score": 308.06
    },
    {
      "id": 37,
      "ml_score": 313.32
    },
    {
      "id": 38,
      "ml_score": 334.25
    },
    {
      "id": 39,
      "ml_score": 235.89
    },
    {
      "id": 40,
      "ml_score": 263.75
    },
    {
      "id": 41,
      "ml_score": 234.66
    },
    {
      "id": 42,
      "ml_score": 250.56
    },
    {
      "id": 43,
      "ml_score": 180.53
    },
    {
      "id": 44,
      "ml_score": 190.34
    },
    {
      "id": 45,
      "ml_score": 197.36
    },
    {
      "id": 46,
      "ml_score": 192.9
    },
    {
      "id": 47,
      "ml_score": 256.7
    },
    {
      "id": 48,
      "ml_score": 159.57
    },
    {
      "id": 49,
      "ml_score": 330.13
    },
    {
      "id": 50,
      "ml_score": 246.34
    },
    {
      "id": 51,
      "ml_score": 213.17
    },
    {
      "id": 52,
      "ml_score": 257.26
    },
    {
      "id": 53,
      "ml_score": 259.08
    },
    {
      "id": 54,
      "ml_score": 207.98
    },
    {
      "id": 55,
      "ml_score": 192.2
    },
    {
      "id": 56,
      "ml_score": 137.08
    },
    {
      "id": 57,
      "ml_score": 235.34
    },
    {
      "id": 58,
      "ml_score": 212.44
    },
    {
      "id": 59,
      "ml_score": 280.72
    },
    {
      "id": 60,
      "ml_score": 277.61
    },
    {
      "id": 61,
      "ml_score": 203.54
    },
    {
      "id": 62,
      "ml_score": 238.8
    },
    {
      "id": 63,
      "ml_score": 170.87
    },
    {
      "id": 64,
      "ml_score": 177.6
    },
    {
      "id": 65,
      "ml_score": 178.46
    },
    {
      "id": 66,
      "ml_score": 130.64
    },
    {
      "id": 67,
      "ml_score": 314.81
    },
    {
      "id": 68,
      "ml_score": 191.17
    },
    {
      "id": 69,
      "ml_score": 322.24
    },
    {
      "id": 70,
      "ml_score": 248.47
    },
    {
      "id": 71,
      "ml_score": 182.48
    },
    {
      "id": 72,
      "ml_score": 248.95
    },
    {
      "id": 73,
      "ml_score": 260.86
    },
    {
      "id": 74,
      "ml_score": 198.11
    },
    {
      "id": 75,
      "ml_score": 201.92
    },
    {
      "id": 76,
      "ml_score": 193.98
    },
    {
      "id": 77,
      "ml_score": 135.41
    },
    {
      "id": 78,
      "ml_score": 212.97
    },
    {
      "id": 79,
      "ml_score": 292.83
    },
    {
      "id": 80,
      "ml_score": 246.01
    },
    {
      "id": 81,
      "ml_score": 188.89
    },
    {
      "id": 82,
      "ml_score": 241.3
    },
    {
      "id": 83,
      "ml_score": 256.36
    },
    {
      "id": 84,
      "ml_score": 181.75
    },
    {
      "id": 85,
      "ml_score": 194.04
    },
    {
      "id": 86,
      "ml_score": 177.7
    },
    {
      "id": 87,
      "ml_score": 188.85
    },
    {
      "id": 88,
      "ml_score": 142.56
    },
    {
      "id": 89,
      "ml_score": 295.05
    },
    {
      "id": 90,
      "ml_score": 298.81
    },
    {
      "id": 91,
      "ml_score": 273.98
    },
    {
      "id": 92,
      "ml_score": 293.38
    },
    {
      "id": 93,
      "ml_score": 247
    },
    {
      "id": 94,
      "ml_score": 194.79
    },
    {
      "id": 95,
      "ml_score": 200.66
    },
    {
      "id": 96,
      "ml_score": 201.85
    },
    {
      "id": 97,
      "ml_score": 187.39
    },
    {
      "id": 98,
      "ml_score": 136.49
    },
    {
      "id": 99,
      "ml_score": 285.96
    },
    {
      "id": 100,
      "ml_score": 209.58
    },
    {
      "id": 101,
      "ml_score": 251.82
    },
    {
      "id": 102,
      "ml_score": 207.23
    },
    {
      "id": 103,
      "ml_score": 209.7
    },
    {
      "id": 104,
      "ml_score": 256.04
    },
    {
      "id": 105,
      "ml_score": 182.47
    },
    {
      "id": 106,
      "ml_score": 186.43
    },
    {
      "id": 107,
      "ml_score": 191.34
    },
    {
      "id": 108,
      "ml_score": 133.95
    },
    {
      "id": 109,
      "ml_score": 283.25
    },
    {
      "id": 110,
      "ml_score": 203.93
    },
    {
      "id": 111,
      "ml_score": 225.47
    },
    {
      "id": 112,
      "ml_score": 198.88
    },
    {
      "id": 113,
      "ml_score": 178.08
    },
    {
      "id": 114,
      "ml_score": 166.99
    },
    {
      "id": 115,
      "ml_score": 162.68
    },
    {
      "id": 116,
      "ml_score": 185.89
    },
    {
      "id": 117,
      "ml_score": 171.66
    },
    {
      "id": 118,
      "ml_score": 135.11
    },
    {
      "id": 119,
      "ml_score": 270.94
    },
    {
      "id": 120,
      "ml_score": 234.1
    },
    {
      "id": 121,
      "ml_score": 254.12
    },
    {
      "id": 122,
      "ml_score": 284.13
    },
    {
      "id": 123,
      "ml_score": 204.02
    },
    {
      "id": 124,
      "ml_score": 240.3
    },
    {
      "id": 125,
      "ml_score": 225.1
    },
    {
      "id": 126,
      "ml_score": 181.4
    },
    {
      "id": 127,
      "ml_score": 185.01
    },
    {
      "id": 128,
      "ml_score": 120.45
    },
    {
      "id": 129,
      "ml_score": 292.5
    },
    {
      "id": 130,
      "ml_score": 292.95
    },
    {
      "id": 131,
      "ml_score": 336.17
    },
    {
      "id": 132,
      "ml_score": 280.56
    },
    {
      "id": 133,
      "ml_score": 206.96
    },
    {
      "id": 134,
      "ml_score": 203.04
    },
    {
      "id": 135,
      "ml_score": 205.49
    },
    {
      "id": 136,
      "ml_score": 204.08
    },
    {
      "id": 137,
      "ml_score": 196.15
    },
    {
      "id": 138,
      "ml_score": 136.15
    },
    {
      "id": 139,
      "ml_score": 209.47
    },
    {
      "id": 140,
      "ml_score": 284.73
    },
    {
      "id": 141,
      "ml_score": 259.73
    },
    {
      "id": 142,
      "ml_score": 237.42
    },
    {
      "id": 143,
      "ml_score": 215.63
    },
    {
      "id": 144,
      "ml_score": 182.58
    },
    {
      "id": 145,
      "ml_score": 182.1
    },
    {
      "id": 146,
      "ml_score": 170.54
    },
    {
      "id": 147,
      "ml_score": 184.11
    },
    {
      "id": 148,
      "ml_score": 162.67
    },
    {
      "id": 149,
      "ml_score": 213.31
    },
    {
      "id": 150,
      "ml_score": 275.38
    },
    {
      "id": 151,
      "ml_score": 219.52
    },
    {
      "id": 152,
      "ml_score": 250.21
    },
    {
      "id": 153,
      "ml_score": 224.46
    },
    {
      "id": 154,
      "ml_score": 174.6
    },
    {
      "id": 155,
      "ml_score": 170.47
    },
    {
      "id": 156,
      "ml_score": 170.74
    },
    {
      "id": 157,
      "ml_score": 167.44
    },
    {
      "id": 158,
      "ml_score": 117.6
    },
    {
      "id": 159,
      "ml_score": 212.39
    },
    {
      "id": 160,
      "ml_score": 230.23
    },
    {
      "id": 161,
      "ml_score": 230.8
    },
    {
      "id": 162,
      "ml_score": 234.16
    },
    {
      "id": 163,
      "ml_score": 198.14
    },
    {
      "id": 164,
      "ml_score": 194.87
    },
    {
      "id": 165,
      "ml_score": 179.61
    },
    {
      "id": 166,
      "ml_score": 174.47
    },
    {
      "id": 167,
      "ml_score": 198.11
    },
    {
      "id": 168,
      "ml_score": 128.97
    },
    {
      "id": 169,
      "ml_score": 266.95
    },
    {
      "id": 170,
      "ml_score": 249.25
    },
    {
      "id": 171,
      "ml_score": 217.87
    },
    {
      "id": 172,
      "ml_score": 241.84
    },
    {
      "id": 173,
      "ml_score": 245.7
    },
    {
      "id": 174,
      "ml_score": 208.6
    },
    {
      "id": 175,
      "ml_score": 172.28
    },
    {
      "id": 176,
      "ml_score": 164.71
    },
    {
      "id": 177,
      "ml_score": 158.93
    },
    {
      "id": 178,
      "ml_score": 143.52
    },
    {
      "id": 179,
      "ml_score": 225.52
    },
    {
      "id": 180,
      "ml_score": 177.61
    },
    {
      "id": 181,
      "ml_score": 222.67
    },
    {
      "id": 182,
      "ml_score": 223.85
    },
    {
      "id": 183,
      "ml_score": 240.38
    },
    {
      "id": 184,
      "ml_score": 150.16
    },
    {
      "id": 185,
      "ml_score": 154.64
    },
    {
      "id": 186,
      "ml_score": 127.95
    },
    {
      "id": 187,
      "ml_score": 303.18
    },
    {
      "id": 188,
      "ml_score": 203.53
    },
    {
      "id": 189,
      "ml_score": 294.67
    },
    {
      "id": 190,
      "ml_score": 267.28
    },
    {
      "id": 191,
      "ml_score": 211.65
    },
    {
      "id": 192,
      "ml_score": 190.12
    },
    {
      "id": 193,
      "ml_score": 300.35
    },
    {
      "id": 194,
      "ml_score": 292.37
    },
    {
      "id": 195,
      "ml_score": 197.48
    },
    {
      "id": 196,
      "ml_score": 213.98
    },
    {
      "id": 197,
      "ml_score": 184.54
    },
    {
      "id": 198,
      "ml_score": 231.93
    },
    {
      "id": 199,
      "ml_score": 157.34
    },
    {
      "id": 200,
      "ml_score": 205.77
    }
  ],
  "meta": {
    "model_type": "RandomForestRegressor",
    "features_used": [
      "goals",
      "assists",
      "minutes",
      "avg_rating",
      "shots_on_target",
      "key_passes",
      "dribbles_completed",
      "tackles",
      "interceptions",
      "clean_sheets",
      "team_trophies",
      "ucl_stage_score",
      "league_strength"
    ],
    "metrics": {
      "mae": 14.7861,
      "r2": 0.8678
    },
    "trained_at": "2026-02-28T12:35:44.050042"
  }
}