[
  {
    "id": 1,
    "name": "James Rodriguez",
    "team": "Manchester City",
    "league": "Premier League",
    "position": "Forward",
    "age": 33,
    "minutesPlayed": 2697,
    "goals": 4,
    "assists": 7,
    "rating": 7.9,
    "passes": 484,
    "tackles": 26,
    "interceptions": 6,
    "dribbles": 105,
    "keyPasses": 57,
    "shots": 75,
    "shotsOnTarget": 22,
    "cleanSheets": 0,
    "yellowCards": 1,
    "redCards": 1
  },
  {
    "id": 2,
    "name": "Luka Modric",
    "team": "Arsenal",
    "league": "Premier League",
    "position": "Forward",
    "age": 22,
    "minutesPlayed": 2362,
    "goals": 26,
    "assists": 2,
    "rating": 8.3,
    "passes": 783,
    "tackles": 30,
    "interceptions": 18,
    "dribbles": 94,
    "keyPasses": 24,
    "shots": 133,
    "shotsOnTarget": 53,
    "cleanSheets": 0,
    "yellowCards": 3,
    "redCards": 1
  },
  {
    "id": 3,
    "name": "Karim Benzema",
    "team": "Liverpool",
    "league": "Premier League",
    "position": "Forward",
    "age": 31,
    "minutesPlayed": 2831,
    "goals": 5,
    "assists": 6,
    "rating": 8.1,
    "passes": 529,
    "tackles": 22,
    "interceptions": 7,
    "dribbles": 103,
    "keyPasses": 36,
    "shots": 32,
    "shotsOnTarget": 16,
    "cleanSheets": 0,
    "yellowCards": 6,
    "redCards": 0
  },
  {
    "id": 4,
    "name": "Vinicius Junior",
    "team": "Chelsea",
    "league": "Premier League",
    "position": "Forward",
    "age": 28,
    "minutesPlayed": 2540,
    "goals": 9,
    "assists": 3,
    "rating": 7.9,
    "passes": 408,
    "tackles": 8,
    "interceptions": 19,
    "dribbles": 30,
    "keyPasses": 56,
    "shots": 97,
    "shotsOnTarget": 29,
    "cleanSheets": 0,
    "yellowCards": 1,
    "redCards": 0
  },
  {
    "id": 5,
    "name": "Erling Haaland",
    "team": "Real Madrid",
    "league": "La Liga",
    "position": "Forward",
    "age": 34,
    "minutesPlayed": 2411,
    "goals": 14,
    "assists": 9,
    "rating": 8.3,
    "passes": 773,
    "tackles": 28,
    "interceptions": 12,
    "dribbles": 50,
    "keyPasses": 59,
    "shots": 136,
    "shotsOnTarget": 54,
    "cleanSheets": 0,
    "yellowCards": 5,
    "redCards": 1
  },
  {
    "id": 6,
    "name": "Mohamed Salah",
    "team": "Barcelona",
    "league": "La Liga",
    "position": "Forward",
    "age": 31,
    "minutesPlayed": 1005,
    "goals": 15,
    "assists": 11,
    "rating": 8.5,
    "passes": 1107,
    "tackles": 17,
    "interceptions": 7,
    "dribbles": 74,
    "keyPasses": 56,
    "shots": 93,
    "shotsOnTarget": 37,
    "cleanSheets": 0,
    "yellowCards": 8,
    "redCards": 0
  },
  {
    "id": 7,
    "name": "Marcus Rashford",
    "team": "Atletico Madrid",
    "league": "La Liga",
    "position": "Forward",
    "age": 27,
    "minutesPlayed": 2095,
    "goals": 12,
    "assists": 1,
    "rating": 7.9,
    "passes": 509,
    "tackles": 11,
    "interceptions": 3,
    "dribbles": 88,
    "keyPasses": 42,
    "shots": 56,
    "shotsOnTarget": 16,
    "cleanSheets": 0,
    "yellowCards": 5,
    "redCards": 0
  },
  {
    "id": 8,
    "name": "Bruno Fernandes",
    "team": "Bayern Munich",
    "league": "Bundesliga",
    "position": "Forward",
    "age": 28,
    "minutesPlayed": 833,
    "goals": 3,
    "assists": 5,
    "rating": 7.9,
    "passes": 522,
    "tackles": 28,
    "interceptions": 19,
    "dribbles": 111,
    "keyPasses": 52,
    "shots": 79,
    "shotsOnTarget": 23,
    "cleanSheets": 0,
    "yellowCards": 7,
    "redCards": 0
  },
  {
    "id": 9,
    "name": "Declan Rice",
    "team": "Borussia Dortmund",
    "league": "Bundesliga",
    "position": "Forward",
    "age": 35,
    "minutesPlayed": 505,
    "goals": 20,
    "assists": 1,
    "rating": 8.1,
    "passes": 716,
    "tackles": 22,
    "interceptions": 4,
    "dribbles": 113,
    "keyPasses": 47,
    "shots": 50,
    "shotsOnTarget": 15,
    "cleanSheets": 0,
    "yellowCards": 3,
    "redCards": 0
  },
  {
    "id": 10,
    "name": "Phil Foden",
    "team": "RB Leipzig",
    "league": "Bundesliga",
    "position": "Forward",
    "age": 19,
    "minutesPlayed": 1887,
    "goals": 14,
    "assists": 11,
    "rating": 7,
    "passes": 1173,
    "tackles": 18,
    "interceptions": 9,
    "dribbles": 70,
    "keyPasses": 27,
    "shots": 129,
    "shotsOnTarget": 51,
    "cleanSheets": 0,
    "yellowCards": 7,
    "redCards": 1
  },
  {
    "id": 11,
    "name": "Jadon Sancho",
    "team": "Juventus",
    "league": "Serie A",
    "position": "Forward",
    "age": 31,
    "minutesPlayed": 1756,
    "goals": 3,
    "assists": 5,
    "rating": 7.2,
    "passes": 876,
    "tackles": 14,
    "interceptions": 3,
    "dribbles": 80,
    "keyPasses": 52,
    "shots": 109,
    "shotsOnTarget": 32,
    "cleanSheets": 0,
    "yellowCards": 7,
    "redCards": 1
  },
  {
    "id": 12,
    "name": "Bukayo Saka",
    "team": "AC Milan",
    "league": "Serie A",
    "position": "Forward",
    "age": 31,
    "minutesPlayed": 778,
    "goals": 8,
    "assists": 11,
    "rating": 7,
    "passes": 1114,
    "tackles": 11,
    "interceptions": 13,
    "dribbles": 85,
    "keyPasses": 40,
    "shots": 113,
    "shotsOnTarget": 45,
    "cleanSheets": 0,
    "yellowCards": 8,
    "redCards": 1
  },
  {
    "id": 13,
    "name": "Martin Odegaard",
    "team": "Inter Milan",
    "league": "Serie A",
    "position": "Forward",
    "age": 32,
    "minutesPlayed": 2426,
    "goals": 8,
    "assists": 2,
    "rating": 7.4,
    "passes": 948,
    "tackles": 15,
    "interceptions": 12,
    "dribbles": 75,
    "keyPasses": 37,
    "shots": 88,
    "shotsOnTarget": 44,
    "cleanSheets": 0,
    "yellowCards": 1,
    "redCards": 0
  },
  {
    "id": 14,
    "name": "Gabriel Jesus",
    "team": "Napoli",
    "league": "Serie A",
    "position": "Forward",
    "age": 36,
    "minutesPlayed": 2754,
    "goals": 5,
    "assists": 9,
    "rating": 7.6,
    "passes": 440,
    "tackles": 19,
    "interceptions": 8,
    "dribbles": 118,
    "keyPasses": 10,
    "shots": 119,
    "shotsOnTarget": 47,
    "cleanSheets": 0,
    "yellowCards": 5,
    "redCards": 0
  },
  {
    "id": 15,
    "name": "Bernardo Silva",
    "team": "Paris Saint-Germain",
    "league": "Ligue 1",
    "position": "Forward",
    "age": 29,
    "minutesPlayed": 2726,
    "goals": 6,
    "assists": 14,
    "rating": 7.3,
    "passes": 416,
    "tackles": 9,
    "interceptions": 4,
    "dribbles": 95,
    "keyPasses": 27,
    "shots": 74,
    "shotsOnTarget": 29,
    "cleanSheets": 0,
    "yellowCards": 6,
    "redCards": 1
  },
  {
    "id": 16,
    "name": "Rodri Hernandez",
    "team": "AS Monaco",
    "league": "Ligue 1",
    "position": "Forward",
    "age": 23,
    "minutesPlayed": 1403,
    "goals": 9,
    "assists": 7,
    "rating": 7.4,
    "passes": 647,
    "tackles": 16,
    "interceptions": 4,
    "dribbles": 35,
    "keyPasses": 13,
    "shots": 76,
    "shotsOnTarget": 30,
    "cleanSheets": 0,
    "yellowCards": 4,
    "redCards": 0
  },
  {
    "id": 17,
    "name": "Kevin De Bruyne",
    "team": "Benfica",
    "league": "Primeira Liga",
    "position": "Forward",
    "age": 31,
    "minutesPlayed": 821,
    "goals": 7,
    "assists": 5,
    "rating": 6.7,
    "passes": 588,
    "tackles": 17,
    "interceptions": 14,
    "dribbles": 88,
    "keyPasses": 33,
    "shots": 33,
    "shotsOnTarget": 9,
    "cleanSheets": 0,
    "yellowCards": 4,
    "redCards": 1
  },
  {
    "id": 18,
    "name": "Julian Alvarez",
    "team": "Porto",
    "league": "Primeira Liga",
    "position": "Forward",
    "age": 22,
    "minutesPlayed": 2157,
    "goals": 18,
    "assists": 12,
    "rating": 7.1,
    "passes": 723,
    "tackles": 8,
    "interceptions": 15,
    "dribbles": 62,
    "keyPasses": 55,
    "shots": 119,
    "shotsOnTarget": 47,
    "cleanSheets": 0,
    "yellowCards": 4,
    "redCards": 1
  },
  {
    "id": 19,
    "name": "Florian Wirtz",
    "team": "Ajax",
    "league": "Eredivisie",
    "position": "Forward",
    "age": 31,
    "minutesPlayed": 1284,
    "goals": 24,
    "assists": 11,
    "rating": 8.8,
    "passes": 525,
    "tackles": 30,
    "interceptions": 7,
    "dribbles": 27,
    "keyPasses": 35,
    "shots": 129,
    "shotsOnTarget": 51,
    "cleanSheets": 0,
    "yellowCards": 8,
    "redCards": 0
  },
  {
    "id": 20,
    "name": "Thomas Muller",
    "team": "Galatasaray",
    "league": "Super Lig",
    "position": "Forward",
    "age": 24,
    "minutesPlayed": 1896,
    "goals": 8,
    "assists": 3,
    "rating": 7.1,
    "passes": 443,
    "tackles": 17,
    "interceptions": 20,
    "dribbles": 42,
    "keyPasses": 12,
    "shots": 47,
    "shotsOnTarget": 23,
    "cleanSheets": 0,
    "yellowCards": 4,
    "redCards": 1
  },
  {
    "id": 21,
    "name": "Kylian Mbappe",
    "team": "Manchester City",
    "league": "Premier League",
    "position": "Forward",
    "age": 25,
    "minutesPlayed": 2684,
    "goals": 23,
    "assists": 10,
    "rating": 7.5,
    "passes": 627,
    "tackles": 20,
    "interceptions": 2,
    "dribbles": 43,
    "keyPasses": 25,
    "shots": 68,
    "shotsOnTarget": 27,
    "cleanSheets": 0,
    "yellowCards": 4,
    "redCards": 0
  },
  {
    "id": 22,
    "name": "Ousmane Dembele",
    "team": "Arsenal",
    "league": "Premier League",
    "position": "Forward",
    "age": 27,
    "minutesPlayed": 1218,
    "goals": 3,
    "assists": 2,
    "rating": 6.8,
    "passes": 466,
    "tackles": 29,
    "interceptions": 18,
    "dribbles": 102,
    "keyPasses": 19,
    "shots": 126,
    "shotsOnTarget": 63,
    "cleanSheets": 0,
    "yellowCards": 7,
    "redCards": 1
  },
  {
    "id": 23,
    "name": "Antoine Griezmann",
    "team": "Liverpool",
    "league": "Premier League",
    "position": "Forward",
    "age": 27,
    "minutesPlayed": 2136,
    "goals": 18,
    "assists": 5,
    "rating": 7.3,
    "passes": 838,
    "tackles": 11,
    "interceptions": 12,
    "dribbles": 119,
    "keyPasses": 29,
    "shots": 87,
    "shotsOnTarget": 34,
    "cleanSheets": 0,
    "yellowCards": 2,
    "redCards": 1
  },
  {
    "id": 24,
    "name": "Pedri Gonzalez",
    "team": "Chelsea",
    "league": "Premier League",
    "position": "Forward",
    "age": 33,
    "minutesPlayed": 1053,
    "goals": 11,
    "assists": 6,
    "rating": 7.2,
    "passes": 747,
    "tackles": 11,
    "interceptions": 8,
    "dribbles": 102,
    "keyPasses": 34,
    "shots": 71,
    "shotsOnTarget": 35,
    "cleanSheets": 0,
    "yellowCards": 3,
    "redCards": 0
  },
  {
    "id": 25,
    "name": "Gavi Lopez",
    "team": "Real Madrid",
    "league": "La Liga",
    "position": "Forward",
    "age": 26,
    "minutesPlayed": 2229,
    "goals": 28,
    "assists": 10,
    "rating": 6.7,
    "passes": 711,
    "tackles": 20,
    "interceptions": 9,
    "dribbles": 59,
    "keyPasses": 30,
    "shots": 68,
    "shotsOnTarget": 34,
    "cleanSheets": 0,
    "yellowCards": 3,
    "redCards": 1
  },
  {
    "id": 26,
    "name": "Robert Lewandowski",
    "team": "Barcelona",
    "league": "La Liga",
    "position": "Forward",
    "age": 31,
    "minutesPlayed": 1324,
    "goals": 3,
    "assists": 1,
    "rating": 7.8,
    "passes": 803,
    "tackles": 7,
    "interceptions": 7,
    "dribbles": 92,
    "keyPasses": 31,
    "shots": 129,
    "shotsOnTarget": 51,
    "cleanSheets": 0,
    "yellowCards": 5,
    "redCards": 0
  },
  {
    "id": 27,
    "name": "Alphonso Davies",
    "team": "Atletico Madrid",
    "league": "La Liga",
    "position": "Forward",
    "age": 21,
    "minutesPlayed": 1438,
    "goals": 12,
    "assists": 11,
    "rating": 6.8,
    "passes": 494,
    "tackles": 16,
    "interceptions": 2,
    "dribbles": 26,
    "keyPasses": 11,
    "shots": 44,
    "shotsOnTarget": 22,
    "cleanSheets": 0,
    "yellowCards": 7,
    "redCards": 0
  },
  {
    "id": 28,
    "name": "Leroy Sane",
    "team": "Bayern Munich",
    "league": "Bundesliga",
    "position": "Forward",
    "age": 30,
    "minutesPlayed": 767,
    "goals": 11,
    "assists": 10,
    "rating": 8.2,
    "passes": 1151,
    "tackles": 30,
    "interceptions": 18,
    "dribbles": 94,
    "keyPasses": 26,
    "shots": 130,
    "shotsOnTarget": 52,
    "cleanSheets": 0,
    "yellowCards": 2,
    "redCards": 0
  },
  {
    "id": 29,
    "name": "Serge Gnabry",
    "team": "Borussia Dortmund",
    "league": "Bundesliga",
    "position": "Forward",
    "age": 21,
    "minutesPlayed": 2930,
    "goals": 21,
    "assists": 9,
    "rating": 8.5,
    "passes": 713,
    "tackles": 12,
    "interceptions": 19,
    "dribbles": 49,
    "keyPasses": 41,
    "shots": 116,
    "shotsOnTarget": 58,
    "cleanSheets": 0,
    "yellowCards": 7,
    "redCards": 0
  },
  {
    "id": 30,
    "name": "Joshua Kimmich",
    "team": "RB Leipzig",
    "league": "Bundesliga",
    "position": "Forward",
    "age": 33,
    "minutesPlayed": 715,
    "goals": 13,
    "assists": 13,
    "rating": 7.3,
    "passes": 830,
    "tackles": 9,
    "interceptions": 16,
    "dribbles": 20,
    "keyPasses": 45,
    "shots": 132,
    "shotsOnTarget": 52,
    "cleanSheets": 0,
    "yellowCards": 8,
    "redCards": 1
  },
  {
    "id": 31,
    "name": "Jude Bellingham",
    "team": "Juventus",
    "league": "Serie A",
    "position": "Forward",
    "age": 25,
    "minutesPlayed": 506,
    "goals": 5,
    "assists": 14,
    "rating": 8.4,
    "passes": 902,
    "tackles": 25,
    "interceptions": 17,
    "dribbles": 120,
    "keyPasses": 13,
    "shots": 59,
    "shotsOnTarget": 23,
    "cleanSheets": 0,
    "yellowCards": 1,
    "redCards": 0
  },
  {
    "id": 32,
    "name": "Harry Kane",
    "team": "AC Milan",
    "league": "Serie A",
    "position": "Forward",
    "age": 20,
    "minutesPlayed": 2886,
    "goals": 6,
    "assists": 2,
    "rating": 7.5,
    "passes": 774,
    "tackles": 6,
    "interceptions": 10,
    "dribbles": 93,
    "keyPasses": 57,
    "shots": 73,
    "shotsOnTarget": 29,
    "cleanSheets": 0,
    "yellowCards": 2,
    "redCards": 1
  },
  {
    "id": 33,
    "name": "Son Heung-Min",
    "team": "Inter Milan",
    "league": "Serie A",
    "position": "Forward",
    "age": 22,
    "minutesPlayed": 1769,
    "goals": 10,
    "assists": 5,
    "rating": 8.4,
    "passes": 885,
    "tackles": 29,
    "interceptions": 6,
    "dribbles": 104,
    "keyPasses": 18,
    "shots": 115,
    "shotsOnTarget": 57,
    "cleanSheets": 0,
    "yellowCards": 4,
    "redCards": 1
  },
  {
    "id": 34,
    "name": "Richarlison De Andrade",
    "team": "Napoli",
    "league": "Serie A",
    "position": "Forward",
    "age": 23,
    "minutesPlayed": 1847,
    "goals": 26,
    "assists": 13,
    "rating": 7.7,
    "passes": 716,
    "tackles": 28,
    "interceptions": 14,
    "dribbles": 34,
    "keyPasses": 36,
    "shots": 49,
    "shotsOnTarget": 24,
    "cleanSheets": 0,
    "yellowCards": 7,
    "redCards": 1
  },
  {
    "id": 35,
    "name": "Dominik Szoboszlai",
    "team": "Paris Saint-Germain",
    "league": "Ligue 1",
    "position": "Forward",
    "age": 34,
    "minutesPlayed": 1445,
    "goals": 27,
    "assists": 6,
    "rating": 7.3,
    "passes": 866,
    "tackles": 30,
    "interceptions": 2,
    "dribbles": 34,
    "keyPasses": 12,
    "shots": 135,
    "shotsOnTarget": 54,
    "cleanSheets": 0,
    "yellowCards": 6,
    "redCards": 1
  },
  {
    "id": 36,
    "name": "Lautaro Martinez",
    "team": "AS Monaco",
    "league": "Ligue 1",
    "position": "Forward",
    "age": 25,
    "minutesPlayed": 1072,
    "goals": 6,
    "assists": 3,
    "rating": 8.7,
    "passes": 965,
    "tackles": 25,
    "interceptions": 7,
    "dribbles": 65,
    "keyPasses": 27,
    "shots": 126,
    "shotsOnTarget": 50,
    "cleanSheets": 0,
    "yellowCards": 8,
    "redCards": 0
  },
  {
    "id": 37,
    "name": "Romelu Lukaku",
    "team": "Benfica",
    "league": "Primeira Liga",
    "position": "Forward",
    "age": 35,
    "minutesPlayed": 1623,
    "goals": 4,
    "assists": 7,
    "rating": 8.5,
    "passes": 982,
    "tackles": 28,
    "interceptions": 8,
    "dribbles": 38,
    "keyPasses": 50,
    "shots": 111,
    "shotsOnTarget": 44,
    "cleanSheets": 0,
    "yellowCards": 5,
    "redCards": 1
  },
  {
    "id": 38,
    "name": "Rafael Leao",
    "team": "Porto",
    "league": "Primeira Liga",
    "position": "Forward",
    "age": 29,
    "minutesPlayed": 1414,
    "goals": 18,
    "assists": 10,
    "rating": 7.5,
    "passes": 444,
    "tackles": 23,
    "interceptions": 15,
    "dribbles": 64,
    "keyPasses": 52,
    "shots": 78,
    "shotsOnTarget": 31,
    "cleanSheets": 0,
    "yellowCards": 8,
    "redCards": 1
  },
  {
    "id": 39,
    "name": "Dusan Vlahovic",
    "team": "Ajax",
    "league": "Eredivisie",
    "position": "Forward",
    "age": 23,
    "minutesPlayed": 2341,
    "goals": 9,
    "assists": 8,
    "rating": 7.6,
    "passes": 788,
    "tackles": 24,
    "interceptions": 15,
    "dribbles": 86,
    "keyPasses": 38,
    "shots": 111,
    "shotsOnTarget": 44,
    "cleanSheets": 0,
    "yellowCards": 3,
    "redCards": 0
  },
  {
    "id": 40,
    "name": "Federico Chiesa",
    "team": "Galatasaray",
    "league": "Super Lig",
    "position": "Forward",
    "age": 36,
    "minutesPlayed": 836,
    "goals": 5,
    "assists": 5,
    "rating": 8.4,
    "passes": 925,
    "tackles": 27,
    "interceptions": 7,
    "dribbles": 36,
    "keyPasses": 43,
    "shots": 114,
    "shotsOnTarget": 45,
    "cleanSheets": 0,
    "yellowCards": 6,
    "redCards": 1
  },
  {
    "id": 41,
    "name": "Nicolo Barella",
    "team": "Manchester City",
    "league": "Premier League",
    "position": "Forward",
    "age": 35,
    "minutesPlayed": 1333,
    "goals": 24,
    "assists": 3,
    "rating": 7.1,
    "passes": 962,
    "tackles": 7,
    "interceptions": 19,
    "dribbles": 50,
    "keyPasses": 31,
    "shots": 51,
    "shotsOnTarget": 20,
    "cleanSheets": 0,
    "yellowCards": 2,
    "redCards": 0
  },
  {
    "id": 42,
    "name": "Sandro Tonali",
    "team": "Arsenal",
    "league": "Premier League",
    "position": "Forward",
    "age": 28,
    "minutesPlayed": 2564,
    "goals": 21,
    "assists": 1,
    "rating": 8.1,
    "passes": 739,
    "tackles": 20,
    "interceptions": 15,
    "dribbles": 94,
    "keyPasses": 53,
    "shots": 75,
    "shotsOnTarget": 30,
    "cleanSheets": 0,
    "yellowCards": 7,
    "redCards": 1
  },
  {
    "id": 43,
    "name": "Alessandro Bastoni",
    "team": "Liverpool",
    "league": "Premier League",
    "position": "Forward",
    "age": 26,
    "minutesPlayed": 1541,
    "goals": 9,
    "assists": 14,
    "rating": 8.6,
    "passes": 995,
    "tackles": 19,
    "interceptions": 3,
    "dribbles": 85,
    "keyPasses": 32,
    "shots": 116,
    "shotsOnTarget": 58,
    "cleanSheets": 0,
    "yellowCards": 6,
    "redCards": 0
  },
  {
    "id": 44,
    "name": "Theo Hernandez",
    "team": "Chelsea",
    "league": "Premier League",
    "position": "Forward",
    "age": 20,
    "minutesPlayed": 1395,
    "goals": 27,
    "assists": 8,
    "rating": 8.4,
    "passes": 630,
    "tackles": 30,
    "interceptions": 3,
    "dribbles": 66,
    "keyPasses": 56,
    "shots": 76,
    "shotsOnTarget": 22,
    "cleanSheets": 0,
    "yellowCards": 6,
    "redCards": 0
  },
  {
    "id": 45,
    "name": "Olivier Giroud",
    "team": "Real Madrid",
    "league": "La Liga",
    "position": "Forward",
    "age": 23,
    "minutesPlayed": 2916,
    "goals": 20,
    "assists": 8,
    "rating": 6.8,
    "passes": 823,
    "tackles": 9,
    "interceptions": 9,
    "dribbles": 32,
    "keyPasses": 34,
    "shots": 140,
    "shotsOnTarget": 56,
    "cleanSheets": 0,
    "yellowCards": 4,
    "redCards": 1
  },
  {
    "id": 46,
    "name": "Achraf Hakimi",
    "team": "Barcelona",
    "league": "La Liga",
    "position": "Forward",
    "age": 19,
    "minutesPlayed": 2728,
    "goals": 9,
    "assists": 8,
    "rating": 8.7,
    "passes": 1085,
    "tackles": 25,
    "interceptions": 10,
    "dribbles": 20,
    "keyPasses": 37,
    "shots": 96,
    "shotsOnTarget": 48,
    "cleanSheets": 0,
    "yellowCards": 4,
    "redCards": 1
  },
  {
    "id": 47,
    "name": "Nuno Mendes",
    "team": "Atletico Madrid",
    "league": "La Liga",
    "position": "Forward",
    "age": 35,
    "minutesPlayed": 2732,
    "goals": 6,
    "assists": 7,
    "rating": 6.5,
    "passes": 773,
    "tackles": 26,
    "interceptions": 17,
    "dribbles": 112,
    "keyPasses": 36,
    "shots": 66,
    "shotsOnTarget": 26,
    "cleanSheets": 0,
    "yellowCards": 8,
    "redCards": 0
  },
  {
    "id": 48,
    "name": "Goncalo Ramos",
    "team": "Bayern Munich",
    "league": "Bundesliga",
    "position": "Forward",
    "age": 22,
    "minutesPlayed": 1288,
    "goals": 18,
    "assists": 11,
    "rating": 8.5,
    "passes": 540,
    "tackles": 12,
    "interceptions": 10,
    "dribbles": 49,
    "keyPasses": 28,
    "shots": 34,
    "shotsOnTarget": 13,
    "cleanSheets": 0,
    "yellowCards": 2,
    "redCards": 1
  },
  {
    "id": 49,
    "name": "Diogo Jota",
    "team": "Borussia Dortmund",
    "league": "Bundesliga",
    "position": "Forward",
    "age": 34,
    "minutesPlayed": 2334,
    "goals": 4,
    "assists": 11,
    "rating": 7.6,
    "passes": 656,
    "tackles": 27,
    "interceptions": 13,
    "dribbles": 72,
    "keyPasses": 10,
    "shots": 75,
    "shotsOnTarget": 37,
    "cleanSheets": 0,
    "yellowCards": 5,
    "redCards": 1
  },
  {
    "id": 50,
    "name": "Ruben Dias",
    "team": "RB Leipzig",
    "league": "Bundesliga",
    "position": "Forward",
    "age": 33,
    "minutesPlayed": 2113,
    "goals": 17,
    "assists": 11,
    "rating": 7.1,
    "passes": 558,
    "tackles": 23,
    "interceptions": 6,
    "dribbles": 89,
    "keyPasses": 22,
    "shots": 130,
    "shotsOnTarget": 39,
    "cleanSheets": 0,
    "yellowCards": 2,
    "redCards": 0
  },
  {
    "id": 51,
    "name": "Frenkie De Jong",
    "team": "Juventus",
    "league": "Serie A",
    "position": "Midfielder",
    "age": 20,
    "minutesPlayed": 1506,
    "goals": 1,
    "assists": 8,
    "rating": 6.9,
    "passes": 814,
    "tackles": 78,
    "interceptions": 46,
    "dribbles": 20,
    "keyPasses": 47,
    "shots": 42,
    "shotsOnTarget": 21,
    "cleanSheets": 0,
    "yellowCards": 8,
    "redCards": 2
  },
  {
    "id": 52,
    "name": "Memphis Depay",
    "team": "AC Milan",
    "league": "Serie A",
    "position": "Midfielder",
    "age": 32,
    "minutesPlayed": 522,
    "goals": 10,
    "assists": 14,
    "rating": 6.7,
    "passes": 1510,
    "tackles": 23,
    "interceptions": 55,
    "dribbles": 56,
    "keyPasses": 27,
    "shots": 69,
    "shotsOnTarget": 20,
    "cleanSheets": 0,
    "yellowCards": 8,
    "redCards": 0
  },
  {
    "id": 53,
    "name": "Steven Bergwijn",
    "team": "Inter Milan",
    "league": "Serie A",
    "position": "Midfielder",
    "age": 27,
    "minutesPlayed": 2241,
    "goals": 3,
    "assists": 10,
    "rating": 7.3,
    "passes": 957,
    "tackles": 30,
    "interceptions": 24,
    "dribbles": 47,
    "keyPasses": 38,
    "shots": 60,
    "shotsOnTarget": 18,
    "cleanSheets": 0,
    "yellowCards": 3,
    "redCards": 1
  },
  {
    "id": 54,
    "name": "Daley Blind",
    "team": "Napoli",
    "league": "Serie A",
    "position": "Midfielder",
    "age": 34,
    "minutesPlayed": 1271,
    "goals": 1,
    "assists": 12,
    "rating": 6.7,
    "passes": 2291,
    "tackles": 52,
    "interceptions": 17,
    "dribbles": 54,
    "keyPasses": 35,
    "shots": 22,
    "shotsOnTarget": 6,
    "cleanSheets": 0,
    "yellowCards": 9,
    "redCards": 0
  },
  {
    "id": 55,
    "name": "Ryan Gravenberch",
    "team": "Paris Saint-Germain",
    "league": "Ligue 1",
    "position": "Midfielder",
    "age": 28,
    "minutesPlayed": 2855,
    "goals": 0,
    "assists": 7,
    "rating": 7.1,
    "passes": 2443,
    "tackles": 35,
    "interceptions": 30,
    "dribbles": 18,
    "keyPasses": 50,
    "shots": 24,
    "shotsOnTarget": 9,
    "cleanSheets": 0,
    "yellowCards": 6,
    "redCards": 1
  },
  {
    "id": 56,
    "name": "Victor Osimhen",
    "team": "AS Monaco",
    "league": "Ligue 1",
    "position": "Midfielder",
    "age": 24,
    "minutesPlayed": 2662,
    "goals": 6,
    "assists": 12,
    "rating": 7.9,
    "passes": 1836,
    "tackles": 82,
    "interceptions": 33,
    "dribbles": 65,
    "keyPasses": 32,
    "shots": 26,
    "shotsOnTarget": 7,
    "cleanSheets": 0,
    "yellowCards": 8,
    "redCards": 1
  },
  {
    "id": 57,
    "name": "Hakim Ziyech",
    "team": "Benfica",
    "league": "Primeira Liga",
    "position": "Midfielder",
    "age": 33,
    "minutesPlayed": 1620,
    "goals": 4,
    "assists": 7,
    "rating": 6.6,
    "passes": 894,
    "tackles": 31,
    "interceptions": 57,
    "dribbles": 57,
    "keyPasses": 53,
    "shots": 21,
    "shotsOnTarget": 8,
    "cleanSheets": 0,
    "yellowCards": 3,
    "redCards": 1
  },
  {
    "id": 58,
    "name": "Youssef En-Nesyri",
    "team": "Porto",
    "league": "Primeira Liga",
    "position": "Midfielder",
    "age": 28,
    "minutesPlayed": 1403,
    "goals": 7,
    "assists": 16,
    "rating": 6.6,
    "passes": 2244,
    "tackles": 53,
    "interceptions": 16,
    "dribbles": 69,
    "keyPasses": 35,
    "shots": 45,
    "shotsOnTarget": 22,
    "cleanSheets": 0,
    "yellowCards": 6,
    "redCards": 2
  },
  {
    "id": 59,
    "name": "Andre Onana",
    "team": "Ajax",
    "league": "Eredivisie",
    "position": "Midfielder",
    "age": 31,
    "minutesPlayed": 1433,
    "goals": 8,
    "assists": 16,
    "rating": 7.3,
    "passes": 1372,
    "tackles": 69,
    "interceptions": 32,
    "dribbles": 78,
    "keyPasses": 51,
    "shots": 11,
    "shotsOnTarget": 4,
    "cleanSheets": 0,
    "yellowCards": 4,
    "redCards": 2
  },
  {
    "id": 60,
    "name": "Darwin Nunez",
    "team": "Galatasaray",
    "league": "Super Lig",
    "position": "Midfielder",
    "age": 20,
    "minutesPlayed": 2372,
    "goals": 12,
    "assists": 5,
    "rating": 7.1,
    "passes": 2006,
    "tackles": 50,
    "interceptions": 44,
    "dribbles": 56,
    "keyPasses": 77,
    "shots": 32,
    "shotsOnTarget": 12,
    "cleanSheets": 0,
    "yellowCards": 10,
    "redCards": 2
  },
  {
    "id": 61,
    "name": "Luis Diaz",
    "team": "Manchester City",
    "league": "Premier League",
    "position": "Midfielder",
    "age": 32,
    "minutesPlayed": 1250,
    "goals": 12,
    "assists": 12,
    "rating": 6.4,
    "passes": 1939,
    "tackles": 29,
    "interceptions": 19,
    "dribbles": 23,
    "keyPasses": 55,
    "shots": 45,
    "shotsOnTarget": 22,
    "cleanSheets": 0,
    "yellowCards": 5,
    "redCards": 2
  },
  {
    "id": 62,
    "name": "Angel Di Maria",
    "team": "Arsenal",
    "league": "Premier League",
    "position": "Midfielder",
    "age": 21,
    "minutesPlayed": 2347,
    "goals": 13,
    "assists": 15,
    "rating": 7.2,
    "passes": 851,
    "tackles": 38,
    "interceptions": 32,
    "dribbles": 64,
    "keyPasses": 20,
    "shots": 66,
    "shotsOnTarget": 19,
    "cleanSheets": 0,
    "yellowCards": 3,
    "redCards": 0
  },
  {
    "id": 63,
    "name": "Cristian Romero",
    "team": "Liverpool",
    "league": "Premier League",
    "position": "Midfielder",
    "age": 32,
    "minutesPlayed": 2907,
    "goals": 9,
    "assists": 9,
    "rating": 6.4,
    "passes": 2169,
    "tackles": 76,
    "interceptions": 23,
    "dribbles": 47,
    "keyPasses": 32,
    "shots": 31,
    "shotsOnTarget": 12,
    "cleanSheets": 0,
    "yellowCards": 2,
    "redCards": 2
  },
  {
    "id": 64,
    "name": "Eduardo Camavinga",
    "team": "Chelsea",
    "league": "Premier League",
    "position": "Midfielder",
    "age": 31,
    "minutesPlayed": 1098,
    "goals": 14,
    "assists": 6,
    "rating": 7.6,
    "passes": 1582,
    "tackles": 80,
    "interceptions": 32,
    "dribbles": 71,
    "keyPasses": 54,
    "shots": 53,
    "shotsOnTarget": 15,
    "cleanSheets": 0,
    "yellowCards": 5,
    "redCards": 0
  },
  {
    "id": 65,
    "name": "Mateo Kovacic",
    "team": "Real Madrid",
    "league": "La Liga",
    "position": "Midfielder",
    "age": 24,
    "minutesPlayed": 1064,
    "goals": 6,
    "assists": 16,
    "rating": 6.6,
    "passes": 816,
    "tackles": 90,
    "interceptions": 39,
    "dribbles": 25,
    "keyPasses": 52,
    "shots": 38,
    "shotsOnTarget": 15,
    "cleanSheets": 0,
    "yellowCards": 9,
    "redCards": 0
  },
  {
    "id": 66,
    "name": "Nicolas Perez",
    "team": "Barcelona",
    "league": "La Liga",
    "position": "Midfielder",
    "age": 21,
    "minutesPlayed": 2092,
    "goals": 3,
    "assists": 7,
    "rating": 7.6,
    "passes": 1624,
    "tackles": 45,
    "interceptions": 25,
    "dribbles": 66,
    "keyPasses": 23,
    "shots": 63,
    "shotsOnTarget": 18,
    "cleanSheets": 0,
    "yellowCards": 4,
    "redCards": 1
  },
  {
    "id": 67,
    "name": "Santiago Valverde",
    "team": "Atletico Madrid",
    "league": "La Liga",
    "position": "Midfielder",
    "age": 35,
    "minutesPlayed": 1692,
    "goals": 8,
    "assists": 13,
    "rating": 6.4,
    "passes": 2344,
    "tackles": 22,
    "interceptions": 40,
    "dribbles": 65,
    "keyPasses": 31,
    "shots": 68,
    "shotsOnTarget": 20,
    "cleanSheets": 0,
    "yellowCards": 8,
    "redCards": 0
  },
  {
    "id": 68,
    "name": "Diego Costa",
    "team": "Bayern Munich",
    "league": "Bundesliga",
    "position": "Midfielder",
    "age": 35,
    "minutesPlayed": 801,
    "goals": 12,
    "assists": 10,
    "rating": 6.9,
    "passes": 1218,
    "tackles": 51,
    "interceptions": 35,
    "dribbles": 43,
    "keyPasses": 45,
    "shots": 35,
    "shotsOnTarget": 17,
    "cleanSheets": 0,
    "yellowCards": 6,
    "redCards": 0
  },
  {
    "id": 69,
    "name": "Alvaro Morata",
    "team": "Borussia Dortmund",
    "league": "Bundesliga",
    "position": "Midfielder",
    "age": 21,
    "minutesPlayed": 1764,
    "goals": 8,
    "assists": 2,
    "rating": 7,
    "passes": 1384,
    "tackles": 90,
    "interceptions": 51,
    "dribbles": 29,
    "keyPasses": 68,
    "shots": 40,
    "shotsOnTarget": 20,
    "cleanSheets": 0,
    "yellowCards": 4,
    "redCards": 0
  },
  {
    "id": 70,
    "name": "Isco Alarcon",
    "team": "RB Leipzig",
    "league": "Bundesliga",
    "position": "Midfielder",
    "age": 26,
    "minutesPlayed": 1735,
    "goals": 6,
    "assists": 7,
    "rating": 7.3,
    "passes": 916,
    "tackles": 70,
    "interceptions": 50,
    "dribbles": 35,
    "keyPasses": 62,
    "shots": 17,
    "shotsOnTarget": 5,
    "cleanSheets": 0,
    "yellowCards": 5,
    "redCards": 2
  },
  {
    "id": 71,
    "name": "Dani Carvajal",
    "team": "Juventus",
    "league": "Serie A",
    "position": "Midfielder",
    "age": 34,
    "minutesPlayed": 2737,
    "goals": 4,
    "assists": 13,
    "rating": 7.9,
    "passes": 1255,
    "tackles": 77,
    "interceptions": 27,
    "dribbles": 74,
    "keyPasses": 55,
    "shots": 31,
    "shotsOnTarget": 9,
    "cleanSheets": 0,
    "yellowCards": 7,
    "redCards": 0
  },
  {
    "id": 72,
    "name": "Marcos Llorente",
    "team": "AC Milan",
    "league": "Serie A",
    "position": "Midfielder",
    "age": 28,
    "minutesPlayed": 2354,
    "goals": 1,
    "assists": 2,
    "rating": 7.7,
    "passes": 2432,
    "tackles": 36,
    "interceptions": 20,
    "dribbles": 73,
    "keyPasses": 56,
    "shots": 29,
    "shotsOnTarget": 8,
    "cleanSheets": 0,
    "yellowCards": 5,
    "redCards": 1
  },
  {
    "id": 73,
    "name": "Aymeric Laporte",
    "team": "Inter Milan",
    "league": "Serie A",
    "position": "Midfielder",
    "age": 27,
    "minutesPlayed": 2041,
    "goals": 12,
    "assists": 13,
    "rating": 6.8,
    "passes": 1141,
    "tackles": 35,
    "interceptions": 52,
    "dribbles": 24,
    "keyPasses": 27,
    "shots": 39,
    "shotsOnTarget": 19,
    "cleanSheets": 0,
    "yellowCards": 7,
    "redCards": 1
  },
  {
    "id": 74,
    "name": "Josko Gvardiol",
    "team": "Napoli",
    "league": "Serie A",
    "position": "Midfielder",
    "age": 19,
    "minutesPlayed": 507,
    "goals": 3,
    "assists": 16,
    "rating": 6.6,
    "passes": 1566,
    "tackles": 65,
    "interceptions": 47,
    "dribbles": 25,
    "keyPasses": 63,
    "shots": 62,
    "shotsOnTarget": 24,
    "cleanSheets": 0,
    "yellowCards": 10,
    "redCards": 1
  },
  {
    "id": 75,
    "name": "Dominic Calvert-Lewin",
    "team": "Paris Saint-Germain",
    "league": "Ligue 1",
    "position": "Midfielder",
    "age": 35,
    "minutesPlayed": 2518,
    "goals": 12,
    "assists": 12,
    "rating": 6.5,
    "passes": 1635,
    "tackles": 84,
    "interceptions": 22,
    "dribbles": 70,
    "keyPasses": 50,
    "shots": 53,
    "shotsOnTarget": 21,
    "cleanSheets": 0,
    "yellowCards": 9,
    "redCards": 1
  },
  {
    "id": 76,
    "name": "Tammy Abraham",
    "team": "AS Monaco",
    "league": "Ligue 1",
    "position": "Midfielder",
    "age": 32,
    "minutesPlayed": 2435,
    "goals": 11,
    "assists": 8,
    "rating": 7.5,
    "passes": 2058,
    "tackles": 71,
    "interceptions": 48,
    "dribbles": 52,
    "keyPasses": 20,
    "shots": 51,
    "shotsOnTarget": 15,
    "cleanSheets": 0,
    "yellowCards": 8,
    "redCards": 1
  },
  {
    "id": 77,
    "name": "Callum Wilson",
    "team": "Benfica",
    "league": "Primeira Liga",
    "position": "Midfielder",
    "age": 23,
    "minutesPlayed": 628,
    "goals": 5,
    "assists": 4,
    "rating": 7,
    "passes": 1064,
    "tackles": 82,
    "interceptions": 21,
    "dribbles": 20,
    "keyPasses": 21,
    "shots": 33,
    "shotsOnTarget": 9,
    "cleanSheets": 0,
    "yellowCards": 10,
    "redCards": 1
  },
  {
    "id": 78,
    "name": "Reece James",
    "team": "Porto",
    "league": "Primeira Liga",
    "position": "Midfielder",
    "age": 21,
    "minutesPlayed": 709,
    "goals": 7,
    "assists": 3,
    "rating": 7.4,
    "passes": 2265,
    "tackles": 51,
    "interceptions": 47,
    "dribbles": 51,
    "keyPasses": 73,
    "shots": 48,
    "shotsOnTarget": 24,
    "cleanSheets": 0,
    "yellowCards": 8,
    "redCards": 0
  },
  {
    "id": 79,
    "name": "Ben Chilwell",
    "team": "Ajax",
    "league": "Eredivisie",
    "position": "Midfielder",
    "age": 33,
    "minutesPlayed": 1280,
    "goals": 10,
    "assists": 14,
    "rating": 6.3,
    "passes": 1855,
    "tackles": 25,
    "interceptions": 37,
    "dribbles": 39,
    "keyPasses": 52,
    "shots": 32,
    "shotsOnTarget": 16,
    "cleanSheets": 0,
    "yellowCards": 6,
    "redCards": 2
  },
  {
    "id": 80,
    "name": "Trent Alexander-Arnold",
    "team": "Galatasaray",
    "league": "Super Lig",
    "position": "Midfielder",
    "age": 19,
    "minutesPlayed": 2807,
    "goals": 10,
    "assists": 16,
    "rating": 6.6,
    "passes": 1832,
    "tackles": 83,
    "interceptions": 56,
    "dribbles": 18,
    "keyPasses": 31,
    "shots": 60,
    "shotsOnTarget": 30,
    "cleanSheets": 0,
    "yellowCards": 2,
    "redCards": 1
  },
  {
    "id": 81,
    "name": "Andrew Robertson",
    "team": "Manchester City",
    "league": "Premier League",
    "position": "Midfielder",
    "age": 27,
    "minutesPlayed": 1356,
    "goals": 12,
    "assists": 3,
    "rating": 7.2,
    "passes": 814,
    "tackles": 62,
    "interceptions": 17,
    "dribbles": 28,
    "keyPasses": 80,
    "shots": 63,
    "shotsOnTarget": 31,
    "cleanSheets": 0,
    "yellowCards": 7,
    "redCards": 1
  },
  {
    "id": 82,
    "name": "Mason Mount",
    "team": "Arsenal",
    "league": "Premier League",
    "position": "Midfielder",
    "age": 30,
    "minutesPlayed": 2593,
    "goals": 7,
    "assists": 3,
    "rating": 7.7,
    "passes": 2071,
    "tackles": 22,
    "interceptions": 32,
    "dribbles": 54,
    "keyPasses": 51,
    "shots": 55,
    "shotsOnTarget": 22,
    "cleanSheets": 0,
    "yellowCards": 6,
    "redCards": 1
  },
  {
    "id": 83,
    "name": "Jack Grealish",
    "team": "Liverpool",
    "league": "Premier League",
    "position": "Midfielder",
    "age": 27,
    "minutesPlayed": 1638,
    "goals": 11,
    "assists": 3,
    "rating": 7.5,
    "passes": 810,
    "tackles": 28,
    "interceptions": 19,
    "dribbles": 70,
    "keyPasses": 77,
    "shots": 54,
    "shotsOnTarget": 21,
    "cleanSheets": 0,
    "yellowCards": 9,
    "redCards": 2
  },
  {
    "id": 84,
    "name": "Emile Smith Rowe",
    "team": "Chelsea",
    "league": "Premier League",
    "position": "Midfielder",
    "age": 30,
    "minutesPlayed": 1654,
    "goals": 0,
    "assists": 13,
    "rating": 6.4,
    "passes": 1453,
    "tackles": 84,
    "interceptions": 32,
    "dribbles": 24,
    "keyPasses": 56,
    "shots": 59,
    "shotsOnTarget": 29,
    "cleanSheets": 0,
    "yellowCards": 6,
    "redCards": 1
  },
  {
    "id": 85,
    "name": "Kieran Trippier",
    "team": "Real Madrid",
    "league": "La Liga",
    "position": "Midfielder",
    "age": 19,
    "minutesPlayed": 861,
    "goals": 10,
    "assists": 5,
    "rating": 7.4,
    "passes": 1233,
    "tackles": 55,
    "interceptions": 54,
    "dribbles": 72,
    "keyPasses": 29,
    "shots": 48,
    "shotsOnTarget": 14,
    "cleanSheets": 0,
    "yellowCards": 9,
    "redCards": 0
  },
  {
    "id": 86,
    "name": "Aaron Ramsdale",
    "team": "Barcelona",
    "league": "La Liga",
    "position": "Midfielder",
    "age": 28,
    "minutesPlayed": 2330,
    "goals": 10,
    "assists": 7,
    "rating": 6.6,
    "passes": 2167,
    "tackles": 51,
    "interceptions": 46,
    "dribbles": 27,
    "keyPasses": 79,
    "shots": 18,
    "shotsOnTarget": 5,
    "cleanSheets": 0,
    "yellowCards": 4,
    "redCards": 0
  },
  {
    "id": 87,
    "name": "William Saliba",
    "team": "Atletico Madrid",
    "league": "La Liga",
    "position": "Midfielder",
    "age": 33,
    "minutesPlayed": 1190,
    "goals": 13,
    "assists": 9,
    "rating": 7.9,
    "passes": 1368,
    "tackles": 36,
    "interceptions": 38,
    "dribbles": 62,
    "keyPasses": 31,
    "shots": 18,
    "shotsOnTarget": 5,
    "cleanSheets": 0,
    "yellowCards": 4,
    "redCards": 2
  },
  {
    "id": 88,
    "name": "Pierre Aubameyang",
    "team": "Bayern Munich",
    "league": "Bundesliga",
    "position": "Midfielder",
    "age": 35,
    "minutesPlayed": 1910,
    "goals": 9,
    "assists": 9,
    "rating": 7.7,
    "passes": 1903,
    "tackles": 89,
    "interceptions": 60,
    "dribbles": 80,
    "keyPasses": 31,
    "shots": 68,
    "shotsOnTarget": 27,
    "cleanSheets": 0,
    "yellowCards": 3,
    "redCards": 2
  },
  {
    "id": 89,
    "name": "Alexandre Lacazette",
    "team": "Borussia Dortmund",
    "league": "Bundesliga",
    "position": "Midfielder",
    "age": 21,
    "minutesPlayed": 1803,
    "goals": 3,
    "assists": 2,
    "rating": 6.4,
    "passes": 1579,
    "tackles": 52,
    "interceptions": 43,
    "dribbles": 25,
    "keyPasses": 58,
    "shots": 27,
    "shotsOnTarget": 10,
    "cleanSheets": 0,
    "yellowCards": 7,
    "redCards": 2
  },
  {
    "id": 90,
    "name": "Youri Tielemans",
    "team": "RB Leipzig",
    "league": "Bundesliga",
    "position": "Midfielder",
    "age": 33,
    "minutesPlayed": 1137,
    "goals": 13,
    "assists": 13,
    "rating": 8,
    "passes": 1623,
    "tackles": 61,
    "interceptions": 30,
    "dribbles": 80,
    "keyPasses": 65,
    "shots": 52,
    "shotsOnTarget": 15,
    "cleanSheets": 0,
    "yellowCards": 10,
    "redCards": 1
  },
  {
    "id": 91,
    "name": "Alexis Sanchez",
    "team": "Juventus",
    "league": "Serie A",
    "position": "Midfielder",
    "age": 25,
    "minutesPlayed": 1661,
    "goals": 13,
    "assists": 16,
    "rating": 7.9,
    "passes": 1193,
    "tackles": 41,
    "interceptions": 38,
    "dribbles": 40,
    "keyPasses": 59,
    "shots": 48,
    "shotsOnTarget": 19,
    "cleanSheets": 0,
    "yellowCards": 3,
    "redCards": 2
  },
  {
    "id": 92,
    "name": "Ferran Torres",
    "team": "AC Milan",
    "league": "Serie A",
    "position": "Midfielder",
    "age": 30,
    "minutesPlayed": 2713,
    "goals": 4,
    "assists": 2,
    "rating": 7.6,
    "passes": 1005,
    "tackles": 50,
    "interceptions": 37,
    "dribbles": 76,
    "keyPasses": 17,
    "shots": 26,
    "shotsOnTarget": 7,
    "cleanSheets": 0,
    "yellowCards": 4,
    "redCards": 2
  },
  {
    "id": 93,
    "name": "Ansu Fati",
    "team": "Inter Milan",
    "league": "Serie A",
    "position": "Midfielder",
    "age": 21,
    "minutesPlayed": 913,
    "goals": 4,
    "assists": 15,
    "rating": 8.1,
    "passes": 1399,
    "tackles": 32,
    "interceptions": 33,
    "dribbles": 67,
    "keyPasses": 68,
    "shots": 57,
    "shotsOnTarget": 17,
    "cleanSheets": 0,
    "yellowCards": 9,
    "redCards": 2
  },
  {
    "id": 94,
    "name": "Ronald Araujo",
    "team": "Napoli",
    "league": "Serie A",
    "position": "Midfielder",
    "age": 28,
    "minutesPlayed": 1375,
    "goals": 10,
    "assists": 8,
    "rating": 7.4,
    "passes": 2186,
    "tackles": 78,
    "interceptions": 56,
    "dribbles": 49,
    "keyPasses": 73,
    "shots": 51,
    "shotsOnTarget": 25,
    "cleanSheets": 0,
    "yellowCards": 6,
    "redCards": 1
  },
  {
    "id": 95,
    "name": "Fede Valverde",
    "team": "Paris Saint-Germain",
    "league": "Ligue 1",
    "position": "Midfielder",
    "age": 26,
    "minutesPlayed": 2217,
    "goals": 11,
    "assists": 4,
    "rating": 7.7,
    "passes": 1052,
    "tackles": 38,
    "interceptions": 30,
    "dribbles": 30,
    "keyPasses": 71,
    "shots": 39,
    "shotsOnTarget": 11,
    "cleanSheets": 0,
    "yellowCards": 8,
    "redCards": 1
  },
  {
    "id": 96,
    "name": "Toni Kroos",
    "team": "AS Monaco",
    "league": "Ligue 1",
    "position": "Midfielder",
    "age": 26,
    "minutesPlayed": 2612,
    "goals": 14,
    "assists": 3,
    "rating": 7.6,
    "passes": 995,
    "tackles": 52,
    "interceptions": 34,
    "dribbles": 34,
    "keyPasses": 72,
    "shots": 28,
    "shotsOnTarget": 11,
    "cleanSheets": 0,
    "yellowCards": 4,
    "redCards": 2
  },
  {
    "id": 97,
    "name": "Antonio Rudiger",
    "team": "Benfica",
    "league": "Primeira Liga",
    "position": "Midfielder",
    "age": 34,
    "minutesPlayed": 2665,
    "goals": 2,
    "assists": 12,
    "rating": 6.3,
    "passes": 2024,
    "tackles": 45,
    "interceptions": 54,
    "dribbles": 55,
    "keyPasses": 41,
    "shots": 28,
    "shotsOnTarget": 8,
    "cleanSheets": 0,
    "yellowCards": 2,
    "redCards": 1
  },
  {
    "id": 98,
    "name": "Eder Militao",
    "team": "Porto",
    "league": "Primeira Liga",
    "position": "Midfielder",
    "age": 36,
    "minutesPlayed": 899,
    "goals": 10,
    "assists": 16,
    "rating": 7.6,
    "passes": 1927,
    "tackles": 83,
    "interceptions": 55,
    "dribbles": 57,
    "keyPasses": 77,
    "shots": 65,
    "shotsOnTarget": 32,
    "cleanSheets": 0,
    "yellowCards": 3,
    "redCards": 2
  },
  {
    "id": 99,
    "name": "Leonardo Bonucci",
    "team": "Ajax",
    "league": "Eredivisie",
    "position": "Midfielder",
    "age": 26,
    "minutesPlayed": 982,
    "goals": 5,
    "assists": 14,
    "rating": 7.7,
    "passes": 2344,
    "tackles": 75,
    "interceptions": 56,
    "dribbles": 28,
    "keyPasses": 40,
    "shots": 52,
    "shotsOnTarget": 15,
    "cleanSheets": 0,
    "yellowCards": 9,
    "redCards": 0
  },
  {
    "id": 100,
    "name": "Gianluca Scamacca",
    "team": "Galatasaray",
    "league": "Super Lig",
    "position": "Midfielder",
    "age": 30,
    "minutesPlayed": 2318,
    "goals": 7,
    "assists": 14,
    "rating": 7.4,
    "passes": 1448,
    "tackles": 38,
    "interceptions": 60,
    "dribbles": 29,
    "keyPasses": 73,
    "shots": 56,
    "shotsOnTarget": 16,
    "cleanSheets": 0,
    "yellowCards": 5,
    "redCards": 1
  },
  {
    "id": 101,
    "name": "Andrea Belotti",
    "team": "Manchester City",
    "league": "Premier League",
    "position": "Midfielder",
    "age": 26,
    "minutesPlayed": 1167,
    "goals": 4,
    "assists": 11,
    "rating": 7.5,
    "passes": 1206,
    "tackles": 47,
    "interceptions": 46,
    "dribbles": 66,
    "keyPasses": 32,
    "shots": 22,
    "shotsOnTarget": 11,
    "cleanSheets": 0,
    "yellowCards": 5,
    "redCards": 0
  },
  {
    "id": 102,
    "name": "Matteo Pessina",
    "team": "Arsenal",
    "league": "Premier League",
    "position": "Midfielder",
    "age": 24,
    "minutesPlayed": 1232,
    "goals": 12,
    "assists": 4,
    "rating": 6.7,
    "passes": 1519,
    "tackles": 73,
    "interceptions": 60,
    "dribbles": 39,
    "keyPasses": 76,
    "shots": 44,
    "shotsOnTarget": 13,
    "cleanSheets": 0,
    "yellowCards": 4,
    "redCards": 0
  },
  {
    "id": 103,
    "name": "Lorenzo Pellegrini",
    "team": "Liverpool",
    "league": "Premier League",
    "position": "Midfielder",
    "age": 22,
    "minutesPlayed": 2457,
    "goals": 8,
    "assists": 13,
    "rating": 8.1,
    "passes": 1765,
    "tackles": 62,
    "interceptions": 52,
    "dribbles": 76,
    "keyPasses": 30,
    "shots": 35,
    "shotsOnTarget": 10,
    "cleanSheets": 0,
    "yellowCards": 7,
    "redCards": 0
  },
  {
    "id": 104,
    "name": "Ivan Perisic",
    "team": "Chelsea",
    "league": "Premier League",
    "position": "Midfielder",
    "age": 24,
    "minutesPlayed": 714,
    "goals": 1,
    "assists": 3,
    "rating": 7.5,
    "passes": 1091,
    "tackles": 30,
    "interceptions": 49,
    "dribbles": 34,
    "keyPasses": 41,
    "shots": 53,
    "shotsOnTarget": 15,
    "cleanSheets": 0,
    "yellowCards": 2,
    "redCards": 1
  },
  {
    "id": 105,
    "name": "James Rodriguez",
    "team": "Real Madrid",
    "league": "La Liga",
    "position": "Midfielder",
    "age": 29,
    "minutesPlayed": 3000,
    "goals": 2,
    "assists": 9,
    "rating": 7.5,
    "passes": 1159,
    "tackles": 69,
    "interceptions": 43,
    "dribbles": 50,
    "keyPasses": 31,
    "shots": 65,
    "shotsOnTarget": 19,
    "cleanSheets": 0,
    "yellowCards": 3,
    "redCards": 2
  },
  {
    "id": 106,
    "name": "Luka Modric",
    "team": "Barcelona",
    "league": "La Liga",
    "position": "Midfielder",
    "age": 35,
    "minutesPlayed": 774,
    "goals": 14,
    "assists": 9,
    "rating": 7.1,
    "passes": 960,
    "tackles": 88,
    "interceptions": 50,
    "dribbles": 79,
    "keyPasses": 77,
    "shots": 66,
    "shotsOnTarget": 26,
    "cleanSheets": 0,
    "yellowCards": 9,
    "redCards": 1
  },
  {
    "id": 107,
    "name": "Karim Benzema",
    "team": "Atletico Madrid",
    "league": "La Liga",
    "position": "Midfielder",
    "age": 19,
    "minutesPlayed": 2069,
    "goals": 8,
    "assists": 6,
    "rating": 7.5,
    "passes": 1111,
    "tackles": 87,
    "interceptions": 30,
    "dribbles": 79,
    "keyPasses": 57,
    "shots": 15,
    "shotsOnTarget": 4,
    "cleanSheets": 0,
    "yellowCards": 2,
    "redCards": 1
  },
  {
    "id": 108,
    "name": "Vinicius Junior",
    "team": "Bayern Munich",
    "league": "Bundesliga",
    "position": "Midfielder",
    "age": 35,
    "minutesPlayed": 1191,
    "goals": 4,
    "assists": 7,
    "rating": 8.1,
    "passes": 2139,
    "tackles": 85,
    "interceptions": 52,
    "dribbles": 29,
    "keyPasses": 38,
    "shots": 26,
    "shotsOnTarget": 7,
    "cleanSheets": 0,
    "yellowCards": 2,
    "redCards": 2
  },
  {
    "id": 109,
    "name": "Erling Haaland",
    "team": "Borussia Dortmund",
    "league": "Bundesliga",
    "position": "Midfielder",
    "age": 36,
    "minutesPlayed": 851,
    "goals": 10,
    "assists": 16,
    "rating": 8.1,
    "passes": 1916,
    "tackles": 72,
    "interceptions": 39,
    "dribbles": 57,
    "keyPasses": 31,
    "shots": 17,
    "shotsOnTarget": 5,
    "cleanSheets": 0,
    "yellowCards": 4,
    "redCards": 0
  },
  {
    "id": 110,
    "name": "Mohamed Salah",
    "team": "RB Leipzig",
    "league": "Bundesliga",
    "position": "Midfielder",
    "age": 20,
    "minutesPlayed": 745,
    "goals": 3,
    "assists": 14,
    "rating": 6.9,
    "passes": 1742,
    "tackles": 88,
    "interceptions": 41,
    "dribbles": 66,
    "keyPasses": 33,
    "shots": 18,
    "shotsOnTarget": 7,
    "cleanSheets": 0,
    "yellowCards": 3,
    "redCards": 1
  },
  {
    "id": 111,
    "name": "Marcus Rashford",
    "team": "Juventus",
    "league": "Serie A",
    "position": "Defender",
    "age": 21,
    "minutesPlayed": 2822,
    "goals": 4,
    "assists": 7,
    "rating": 7.5,
    "passes": 906,
    "tackles": 110,
    "interceptions": 31,
    "dribbles": 12,
    "keyPasses": 16,
    "shots": 24,
    "shotsOnTarget": 7,
    "cleanSheets": 18,
    "yellowCards": 11,
    "redCards": 2
  },
  {
    "id": 112,
    "name": "Bruno Fernandes",
    "team": "AC Milan",
    "league": "Serie A",
    "position": "Defender",
    "age": 35,
    "minutesPlayed": 575,
    "goals": 1,
    "assists": 6,
    "rating": 6.7,
    "passes": 1425,
    "tackles": 77,
    "interceptions": 81,
    "dribbles": 11,
    "keyPasses": 6,
    "shots": 4,
    "shotsOnTarget": 1,
    "cleanSheets": 14,
    "yellowCards": 11,
    "redCards": 2
  },
  {
    "id": 113,
    "name": "Declan Rice",
    "team": "Inter Milan",
    "league": "Serie A",
    "position": "Defender",
    "age": 35,
    "minutesPlayed": 2190,
    "goals": 4,
    "assists": 6,
    "rating": 6.6,
    "passes": 1993,
    "tackles": 109,
    "interceptions": 65,
    "dribbles": 12,
    "keyPasses": 17,
    "shots": 21,
    "shotsOnTarget": 8,
    "cleanSheets": 3,
    "yellowCards": 10,
    "redCards": 0
  },
  {
    "id": 114,
    "name": "Phil Foden",
    "team": "Napoli",
    "league": "Serie A",
    "position": "Defender",
    "age": 22,
    "minutesPlayed": 2031,
    "goals": 5,
    "assists": 6,
    "rating": 7.2,
    "passes": 798,
    "tackles": 116,
    "interceptions": 30,
    "dribbles": 17,
    "keyPasses": 13,
    "shots": 13,
    "shotsOnTarget": 3,
    "cleanSheets": 9,
    "yellowCards": 4,
    "redCards": 0
  },
  {
    "id": 115,
    "name": "Jadon Sancho",
    "team": "Paris Saint-Germain",
    "league": "Ligue 1",
    "position": "Defender",
    "age": 19,
    "minutesPlayed": 856,
    "goals": 1,
    "assists": 1,
    "rating": 7,
    "passes": 1931,
    "tackles": 94,
    "interceptions": 96,
    "dribbles": 5,
    "keyPasses": 18,
    "shots": 16,
    "shotsOnTarget": 4,
    "cleanSheets": 5,
    "yellowCards": 7,
    "redCards": 0
  },
  {
    "id": 116,
    "name": "Bukayo Saka",
    "team": "AS Monaco",
    "league": "Ligue 1",
    "position": "Defender",
    "age": 26,
    "minutesPlayed": 695,
    "goals": 1,
    "assists": 2,
    "rating": 7.1,
    "passes": 709,
    "tackles": 103,
    "interceptions": 70,
    "dribbles": 17,
    "keyPasses": 22,
    "shots": 4,
    "shotsOnTarget": 1,
    "cleanSheets": 12,
    "yellowCards": 9,
    "redCards": 2
  },
  {
    "id": 117,
    "name": "Martin Odegaard",
    "team": "Benfica",
    "league": "Primeira Liga",
    "position": "Defender",
    "age": 30,
    "minutesPlayed": 1519,
    "goals": 1,
    "assists": 2,
    "rating": 7.3,
    "passes": 902,
    "tackles": 120,
    "interceptions": 79,
    "dribbles": 22,
    "keyPasses": 8,
    "shots": 9,
    "shotsOnTarget": 3,
    "cleanSheets": 17,
    "yellowCards": 11,
    "redCards": 1
  },
  {
    "id": 118,
    "name": "Gabriel Jesus",
    "team": "Porto",
    "league": "Primeira Liga",
    "position": "Defender",
    "age": 31,
    "minutesPlayed": 1472,
    "goals": 2,
    "assists": 1,
    "rating": 6.3,
    "passes": 1753,
    "tackles": 133,
    "interceptions": 90,
    "dribbles": 13,
    "keyPasses": 23,
    "shots": 9,
    "shotsOnTarget": 2,
    "cleanSheets": 17,
    "yellowCards": 3,
    "redCards": 2
  },
  {
    "id": 119,
    "name": "Bernardo Silva",
    "team": "Ajax",
    "league": "Eredivisie",
    "position": "Defender",
    "age": 24,
    "minutesPlayed": 1483,
    "goals": 2,
    "assists": 1,
    "rating": 7.5,
    "passes": 1478,
    "tackles": 96,
    "interceptions": 77,
    "dribbles": 12,
    "keyPasses": 20,
    "shots": 17,
    "shotsOnTarget": 3,
    "cleanSheets": 3,
    "yellowCards": 9,
    "redCards": 2
  },
  {
    "id": 120,
    "name": "Rodri Hernandez",
    "team": "Galatasaray",
    "league": "Super Lig",
    "position": "Defender",
    "age": 34,
    "minutesPlayed": 1837,
    "goals": 2,
    "assists": 6,
    "rating": 7.6,
    "passes": 744,
    "tackles": 86,
    "interceptions": 30,
    "dribbles": 26,
    "keyPasses": 10,
    "shots": 8,
    "shotsOnTarget": 2,
    "cleanSheets": 11,
    "yellowCards": 4,
    "redCards": 2
  },
  {
    "id": 121,
    "name": "Kevin De Bruyne",
    "team": "Manchester City",
    "league": "Premier League",
    "position": "Defender",
    "age": 31,
    "minutesPlayed": 679,
    "goals": 4,
    "assists": 6,
    "rating": 6.9,
    "passes": 1280,
    "tackles": 117,
    "interceptions": 53,
    "dribbles": 24,
    "keyPasses": 23,
    "shots": 6,
    "shotsOnTarget": 1,
    "cleanSheets": 16,
    "yellowCards": 9,
    "redCards": 2
  },
  {
    "id": 122,
    "name": "Julian Alvarez",
    "team": "Arsenal",
    "league": "Premier League",
    "position": "Defender",
    "age": 22,
    "minutesPlayed": 1360,
    "goals": 3,
    "assists": 5,
    "rating": 7.6,
    "passes": 1736,
    "tackles": 74,
    "interceptions": 92,
    "dribbles": 7,
    "keyPasses": 11,
    "shots": 14,
    "shotsOnTarget": 4,
    "cleanSheets": 14,
    "yellowCards": 3,
    "redCards": 0
  },
  {
    "id": 123,
    "name": "Florian Wirtz",
    "team": "Liverpool",
    "league": "Premier League",
    "position": "Defender",
    "age": 35,
    "minutesPlayed": 2015,
    "goals": 3,
    "assists": 7,
    "rating": 6.9,
    "passes": 1235,
    "tackles": 132,
    "interceptions": 85,
    "dribbles": 22,
    "keyPasses": 16,
    "shots": 22,
    "shotsOnTarget": 6,
    "cleanSheets": 3,
    "yellowCards": 8,
    "redCards": 1
  },
  {
    "id": 124,
    "name": "Thomas Muller",
    "team": "Chelsea",
    "league": "Premier League",
    "position": "Defender",
    "age": 31,
    "minutesPlayed": 2462,
    "goals": 3,
    "assists": 3,
    "rating": 7.4,
    "passes": 1864,
    "tackles": 128,
    "interceptions": 48,
    "dribbles": 21,
    "keyPasses": 15,
    "shots": 14,
    "shotsOnTarget": 2,
    "cleanSheets": 12,
    "yellowCards": 11,
    "redCards": 2
  },
  {
    "id": 125,
    "name": "Kylian Mbappe",
    "team": "Real Madrid",
    "league": "La Liga",
    "position": "Defender",
    "age": 29,
    "minutesPlayed": 2843,
    "goals": 4,
    "assists": 5,
    "rating": 6.9,
    "passes": 1073,
    "tackles": 49,
    "interceptions": 76,
    "dribbles": 26,
    "keyPasses": 25,
    "shots": 11,
    "shotsOnTarget": 3,
    "cleanSheets": 16,
    "yellowCards": 6,
    "redCards": 0
  },
  {
    "id": 126,
    "name": "Ousmane Dembele",
    "team": "Barcelona",
    "league": "La Liga",
    "position": "Defender",
    "age": 26,
    "minutesPlayed": 2511,
    "goals": 0,
    "assists": 5,
    "rating": 7.6,
    "passes": 892,
    "tackles": 114,
    "interceptions": 94,
    "dribbles": 18,
    "keyPasses": 16,
    "shots": 11,
    "shotsOnTarget": 2,
    "cleanSheets": 12,
    "yellowCards": 9,
    "redCards": 1
  },
  {
    "id": 127,
    "name": "Antoine Griezmann",
    "team": "Atletico Madrid",
    "league": "La Liga",
    "position": "Defender",
    "age": 23,
    "minutesPlayed": 2424,
    "goals": 3,
    "assists": 0,
    "rating": 6.8,
    "passes": 1498,
    "tackles": 103,
    "interceptions": 64,
    "dribbles": 17,
    "keyPasses": 23,
    "shots": 7,
    "shotsOnTarget": 2,
    "cleanSheets": 5,
    "yellowCards": 5,
    "redCards": 0
  },
  {
    "id": 128,
    "name": "Pedri Gonzalez",
    "team": "Bayern Munich",
    "league": "Bundesliga",
    "position": "Defender",
    "age": 31,
    "minutesPlayed": 774,
    "goals": 2,
    "assists": 0,
    "rating": 7.4,
    "passes": 1379,
    "tackles": 42,
    "interceptions": 32,
    "dribbles": 19,
    "keyPasses": 19,
    "shots": 24,
    "shotsOnTarget": 7,
    "cleanSheets": 10,
    "yellowCards": 10,
    "redCards": 0
  },
  {
    "id": 129,
    "name": "Gavi Lopez",
    "team": "Borussia Dortmund",
    "league": "Bundesliga",
    "position": "Defender",
    "age": 21,
    "minutesPlayed": 723,
    "goals": 1,
    "assists": 1,
    "rating": 7.4,
    "passes": 925,
    "tackles": 132,
    "interceptions": 41,
    "dribbles": 20,
    "keyPasses": 14,
    "shots": 7,
    "shotsOnTarget": 2,
    "cleanSheets": 17,
    "yellowCards": 5,
    "redCards": 2
  },
  {
    "id": 130,
    "name": "Robert Lewandowski",
    "team": "RB Leipzig",
    "league": "Bundesliga",
    "position": "Defender",
    "age": 24,
    "minutesPlayed": 1827,
    "goals": 4,
    "assists": 0,
    "rating": 6.6,
    "passes": 1767,
    "tackles": 70,
    "interceptions": 79,
    "dribbles": 18,
    "keyPasses": 4,
    "shots": 8,
    "shotsOnTarget": 1,
    "cleanSheets": 8,
    "yellowCards": 8,
    "redCards": 2
  },
  {
    "id": 131,
    "name": "Alphonso Davies",
    "team": "Juventus",
    "league": "Serie A",
    "position": "Defender",
    "age": 25,
    "minutesPlayed": 1451,
    "goals": 1,
    "assists": 3,
    "rating": 7.2,
    "passes": 698,
    "tackles": 88,
    "interceptions": 75,
    "dribbles": 21,
    "keyPasses": 10,
    "shots": 24,
    "shotsOnTarget": 9,
    "cleanSheets": 14,
    "yellowCards": 10,
    "redCards": 2
  },
  {
    "id": 132,
    "name": "Leroy Sane",
    "team": "AC Milan",
    "league": "Serie A",
    "position": "Defender",
    "age": 26,
    "minutesPlayed": 2361,
    "goals": 5,
    "assists": 0,
    "rating": 6.9,
    "passes": 883,
    "tackles": 132,
    "interceptions": 63,
    "dribbles": 16,
    "keyPasses": 5,
    "shots": 9,
    "shotsOnTarget": 2,
    "cleanSheets": 17,
    "yellowCards": 6,
    "redCards": 2
  },
  {
    "id": 133,
    "name": "Serge Gnabry",
    "team": "Inter Milan",
    "league": "Serie A",
    "position": "Defender",
    "age": 33,
    "minutesPlayed": 1342,
    "goals": 1,
    "assists": 0,
    "rating": 6.5,
    "passes": 1616,
    "tackles": 137,
    "interceptions": 99,
    "dribbles": 13,
    "keyPasses": 10,
    "shots": 3,
    "shotsOnTarget": 1,
    "cleanSheets": 11,
    "yellowCards": 11,
    "redCards": 0
  },
  {
    "id": 134,
    "name": "Joshua Kimmich",
    "team": "Napoli",
    "league": "Serie A",
    "position": "Defender",
    "age": 25,
    "minutesPlayed": 2214,
    "goals": 0,
    "assists": 3,
    "rating": 7.8,
    "passes": 1724,
    "tackles": 86,
    "interceptions": 98,
    "dribbles": 13,
    "keyPasses": 15,
    "shots": 19,
    "shotsOnTarget": 5,
    "cleanSheets": 6,
    "yellowCards": 4,
    "redCards": 1
  },
  {
    "id": 135,
    "name": "Jude Bellingham",
    "team": "Paris Saint-Germain",
    "league": "Ligue 1",
    "position": "Defender",
    "age": 26,
    "minutesPlayed": 1893,
    "goals": 3,
    "assists": 5,
    "rating": 6.4,
    "passes": 966,
    "tackles": 90,
    "interceptions": 41,
    "dribbles": 26,
    "keyPasses": 24,
    "shots": 16,
    "shotsOnTarget": 6,
    "cleanSheets": 5,
    "yellowCards": 9,
    "redCards": 2
  },
  {
    "id": 136,
    "name": "Harry Kane",
    "team": "AS Monaco",
    "league": "Ligue 1",
    "position": "Defender",
    "age": 34,
    "minutesPlayed": 2814,
    "goals": 4,
    "assists": 7,
    "rating": 6.3,
    "passes": 1968,
    "tackles": 59,
    "interceptions": 91,
    "dribbles": 15,
    "keyPasses": 20,
    "shots": 3,
    "shotsOnTarget": 0,
    "cleanSheets": 3,
    "yellowCards": 12,
    "redCards": 0
  },
  {
    "id": 137,
    "name": "Son Heung-Min",
    "team": "Benfica",
    "league": "Primeira Liga",
    "position": "Defender",
    "age": 23,
    "minutesPlayed": 1670,
    "goals": 0,
    "assists": 0,
    "rating": 6.8,
    "passes": 1914,
    "tackles": 125,
    "interceptions": 59,
    "dribbles": 14,
    "keyPasses": 12,
    "shots": 17,
    "shotsOnTarget": 6,
    "cleanSheets": 3,
    "yellowCards": 8,
    "redCards": 0
  },
  {
    "id": 138,
    "name": "Richarlison De Andrade",
    "team": "Porto",
    "league": "Primeira Liga",
    "position": "Defender",
    "age": 25,
    "minutesPlayed": 653,
    "goals": 4,
    "assists": 1,
    "rating": 7.1,
    "passes": 865,
    "tackles": 75,
    "interceptions": 50,
    "dribbles": 15,
    "keyPasses": 16,
    "shots": 23,
    "shotsOnTarget": 4,
    "cleanSheets": 12,
    "yellowCards": 10,
    "redCards": 2
  },
  {
    "id": 139,
    "name": "Dominik Szoboszlai",
    "team": "Ajax",
    "league": "Eredivisie",
    "position": "Defender",
    "age": 30,
    "minutesPlayed": 1692,
    "goals": 5,
    "assists": 1,
    "rating": 6.4,
    "passes": 1464,
    "tackles": 54,
    "interceptions": 94,
    "dribbles": 29,
    "keyPasses": 21,
    "shots": 9,
    "shotsOnTarget": 2,
    "cleanSheets": 7,
    "yellowCards": 6,
    "redCards": 1
  },
  {
    "id": 140,
    "name": "Lautaro Martinez",
    "team": "Galatasaray",
    "league": "Super Lig",
    "position": "Defender",
    "age": 22,
    "minutesPlayed": 1106,
    "goals": 4,
    "assists": 6,
    "rating": 6.4,
    "passes": 1522,
    "tackles": 47,
    "interceptions": 36,
    "dribbles": 26,
    "keyPasses": 10,
    "shots": 20,
    "shotsOnTarget": 8,
    "cleanSheets": 8,
    "yellowCards": 9,
    "redCards": 0
  },
  {
    "id": 141,
    "name": "Romelu Lukaku",
    "team": "Manchester City",
    "league": "Premier League",
    "position": "Defender",
    "age": 20,
    "minutesPlayed": 2433,
    "goals": 4,
    "assists": 5,
    "rating": 7.1,
    "passes": 1598,
    "tackles": 55,
    "interceptions": 47,
    "dribbles": 21,
    "keyPasses": 16,
    "shots": 9,
    "shotsOnTarget": 2,
    "cleanSheets": 5,
    "yellowCards": 5,
    "redCards": 1
  },
  {
    "id": 142,
    "name": "Rafael Leao",
    "team": "Arsenal",
    "league": "Premier League",
    "position": "Defender",
    "age": 28,
    "minutesPlayed": 522,
    "goals": 3,
    "assists": 5,
    "rating": 6.3,
    "passes": 954,
    "tackles": 47,
    "interceptions": 61,
    "dribbles": 7,
    "keyPasses": 17,
    "shots": 3,
    "shotsOnTarget": 1,
    "cleanSheets": 17,
    "yellowCards": 10,
    "redCards": 2
  },
  {
    "id": 143,
    "name": "Dusan Vlahovic",
    "team": "Liverpool",
    "league": "Premier League",
    "position": "Defender",
    "age": 20,
    "minutesPlayed": 873,
    "goals": 0,
    "assists": 3,
    "rating": 7.4,
    "passes": 1987,
    "tackles": 81,
    "interceptions": 35,
    "dribbles": 8,
    "keyPasses": 21,
    "shots": 5,
    "shotsOnTarget": 1,
    "cleanSheets": 6,
    "yellowCards": 5,
    "redCards": 1
  },
  {
    "id": 144,
    "name": "Federico Chiesa",
    "team": "Chelsea",
    "league": "Premier League",
    "position": "Defender",
    "age": 29,
    "minutesPlayed": 2722,
    "goals": 3,
    "assists": 7,
    "rating": 6.6,
    "passes": 1055,
    "tackles": 48,
    "interceptions": 82,
    "dribbles": 20,
    "keyPasses": 8,
    "shots": 9,
    "shotsOnTarget": 2,
    "cleanSheets": 10,
    "yellowCards": 8,
    "redCards": 1
  },
  {
    "id": 145,
    "name": "Nicolo Barella",
    "team": "Real Madrid",
    "league": "La Liga",
    "position": "Defender",
    "age": 24,
    "minutesPlayed": 1460,
    "goals": 4,
    "assists": 2,
    "rating": 6.4,
    "passes": 1962,
    "tackles": 115,
    "interceptions": 52,
    "dribbles": 18,
    "keyPasses": 22,
    "shots": 7,
    "shotsOnTarget": 2,
    "cleanSheets": 10,
    "yellowCards": 4,
    "redCards": 0
  },
  {
    "id": 146,
    "name": "Sandro Tonali",
    "team": "Barcelona",
    "league": "La Liga",
    "position": "Defender",
    "age": 25,
    "minutesPlayed": 2124,
    "goals": 1,
    "assists": 3,
    "rating": 7,
    "passes": 1265,
    "tackles": 43,
    "interceptions": 71,
    "dribbles": 18,
    "keyPasses": 24,
    "shots": 3,
    "shotsOnTarget": 0,
    "cleanSheets": 10,
    "yellowCards": 7,
    "redCards": 2
  },
  {
    "id": 147,
    "name": "Alessandro Bastoni",
    "team": "Atletico Madrid",
    "league": "La Liga",
    "position": "Defender",
    "age": 33,
    "minutesPlayed": 2877,
    "goals": 0,
    "assists": 6,
    "rating": 6.3,
    "passes": 1248,
    "tackles": 40,
    "interceptions": 37,
    "dribbles": 18,
    "keyPasses": 22,
    "shots": 15,
    "shotsOnTarget": 4,
    "cleanSheets": 5,
    "yellowCards": 5,
    "redCards": 2
  },
  {
    "id": 148,
    "name": "Theo Hernandez",
    "team": "Bayern Munich",
    "league": "Bundesliga",
    "position": "Defender",
    "age": 32,
    "minutesPlayed": 520,
    "goals": 2,
    "assists": 5,
    "rating": 6.6,
    "passes": 1240,
    "tackles": 58,
    "interceptions": 30,
    "dribbles": 22,
    "keyPasses": 10,
    "shots": 3,
    "shotsOnTarget": 1,
    "cleanSheets": 12,
    "yellowCards": 3,
    "redCards": 1
  },
  {
    "id": 149,
    "name": "Olivier Giroud",
    "team": "Borussia Dortmund",
    "league": "Bundesliga",
    "position": "Defender",
    "age": 19,
    "minutesPlayed": 704,
    "goals": 2,
    "assists": 1,
    "rating": 6.6,
    "passes": 1124,
    "tackles": 102,
    "interceptions": 77,
    "dribbles": 17,
    "keyPasses": 9,
    "shots": 6,
    "shotsOnTarget": 2,
    "cleanSheets": 3,
    "yellowCards": 7,
    "redCards": 2
  },
  {
    "id": 150,
    "name": "Achraf Hakimi",
    "team": "RB Leipzig",
    "league": "Bundesliga",
    "position": "Defender",
    "age": 31,
    "minutesPlayed": 1752,
    "goals": 1,
    "assists": 6,
    "rating": 7,
    "passes": 1331,
    "tackles": 45,
    "interceptions": 92,
    "dribbles": 28,
    "keyPasses": 16,
    "shots": 22,
    "shotsOnTarget": 6,
    "cleanSheets": 16,
    "yellowCards": 7,
    "redCards": 2
  },
  {
    "id": 151,
    "name": "Nuno Mendes",
    "team": "Juventus",
    "league": "Serie A",
    "position": "Defender",
    "age": 27,
    "minutesPlayed": 1318,
    "goals": 1,
    "assists": 7,
    "rating": 7.6,
    "passes": 1495,
    "tackles": 110,
    "interceptions": 37,
    "dribbles": 16,
    "keyPasses": 13,
    "shots": 8,
    "shotsOnTarget": 1,
    "cleanSheets": 16,
    "yellowCards": 8,
    "redCards": 2
  },
  {
    "id": 152,
    "name": "Goncalo Ramos",
    "team": "AC Milan",
    "league": "Serie A",
    "position": "Defender",
    "age": 25,
    "minutesPlayed": 1425,
    "goals": 0,
    "assists": 7,
    "rating": 6.9,
    "passes": 1898,
    "tackles": 67,
    "interceptions": 48,
    "dribbles": 17,
    "keyPasses": 12,
    "shots": 5,
    "shotsOnTarget": 1,
    "cleanSheets": 5,
    "yellowCards": 10,
    "redCards": 1
  },
  {
    "id": 153,
    "name": "Diogo Jota",
    "team": "Inter Milan",
    "league": "Serie A",
    "position": "Defender",
    "age": 31,
    "minutesPlayed": 2592,
    "goals": 5,
    "assists": 5,
    "rating": 6.7,
    "passes": 776,
    "tackles": 62,
    "interceptions": 63,
    "dribbles": 29,
    "keyPasses": 22,
    "shots": 7,
    "shotsOnTarget": 1,
    "cleanSheets": 12,
    "yellowCards": 11,
    "redCards": 2
  },
  {
    "id": 154,
    "name": "Ruben Dias",
    "team": "Napoli",
    "league": "Serie A",
    "position": "Defender",
    "age": 36,
    "minutesPlayed": 732,
    "goals": 1,
    "assists": 6,
    "rating": 7.6,
    "passes": 654,
    "tackles": 50,
    "interceptions": 74,
    "dribbles": 29,
    "keyPasses": 22,
    "shots": 9,
    "shotsOnTarget": 2,
    "cleanSheets": 3,
    "yellowCards": 5,
    "redCards": 2
  },
  {
    "id": 155,
    "name": "Frenkie De Jong",
    "team": "Paris Saint-Germain",
    "league": "Ligue 1",
    "position": "Defender",
    "age": 34,
    "minutesPlayed": 1460,
    "goals": 5,
    "assists": 1,
    "rating": 6.4,
    "passes": 777,
    "tackles": 108,
    "interceptions": 45,
    "dribbles": 10,
    "keyPasses": 12,
    "shots": 3,
    "shotsOnTarget": 0,
    "cleanSheets": 17,
    "yellowCards": 9,
    "redCards": 0
  },
  {
    "id": 156,
    "name": "Memphis Depay",
    "team": "AS Monaco",
    "league": "Ligue 1",
    "position": "Defender",
    "age": 27,
    "minutesPlayed": 1761,
    "goals": 2,
    "assists": 6,
    "rating": 7.1,
    "passes": 898,
    "tackles": 106,
    "interceptions": 37,
    "dribbles": 22,
    "keyPasses": 8,
    "shots": 24,
    "shotsOnTarget": 7,
    "cleanSheets": 9,
    "yellowCards": 12,
    "redCards": 1
  },
  {
    "id": 157,
    "name": "Steven Bergwijn",
    "team": "Benfica",
    "league": "Primeira Liga",
    "position": "Defender",
    "age": 33,
    "minutesPlayed": 2608,
    "goals": 2,
    "assists": 5,
    "rating": 7,
    "passes": 1423,
    "tackles": 62,
    "interceptions": 62,
    "dribbles": 24,
    "keyPasses": 6,
    "shots": 10,
    "shotsOnTarget": 4,
    "cleanSheets": 6,
    "yellowCards": 10,
    "redCards": 0
  },
  {
    "id": 158,
    "name": "Daley Blind",
    "team": "Porto",
    "league": "Primeira Liga",
    "position": "Defender",
    "age": 28,
    "minutesPlayed": 1606,
    "goals": 1,
    "assists": 2,
    "rating": 7.5,
    "passes": 1276,
    "tackles": 137,
    "interceptions": 100,
    "dribbles": 26,
    "keyPasses": 9,
    "shots": 7,
    "shotsOnTarget": 2,
    "cleanSheets": 16,
    "yellowCards": 10,
    "redCards": 0
  },
  {
    "id": 159,
    "name": "Ryan Gravenberch",
    "team": "Ajax",
    "league": "Eredivisie",
    "position": "Defender",
    "age": 20,
    "minutesPlayed": 1997,
    "goals": 5,
    "assists": 1,
    "rating": 7.3,
    "passes": 665,
    "tackles": 140,
    "interceptions": 59,
    "dribbles": 8,
    "keyPasses": 10,
    "shots": 22,
    "shotsOnTarget": 6,
    "cleanSheets": 7,
    "yellowCards": 8,
    "redCards": 2
  },
  {
    "id": 160,
    "name": "Victor Osimhen",
    "team": "Galatasaray",
    "league": "Super Lig",
    "position": "Defender",
    "age": 22,
    "minutesPlayed": 2664,
    "goals": 2,
    "assists": 4,
    "rating": 6.3,
    "passes": 1761,
    "tackles": 65,
    "interceptions": 46,
    "dribbles": 23,
    "keyPasses": 15,
    "shots": 24,
    "shotsOnTarget": 4,
    "cleanSheets": 9,
    "yellowCards": 5,
    "redCards": 1
  },
  {
    "id": 161,
    "name": "Hakim Ziyech",
    "team": "Manchester City",
    "league": "Premier League",
    "position": "Defender",
    "age": 33,
    "minutesPlayed": 2868,
    "goals": 0,
    "assists": 4,
    "rating": 6.9,
    "passes": 1393,
    "tackles": 129,
    "interceptions": 47,
    "dribbles": 6,
    "keyPasses": 25,
    "shots": 11,
    "shotsOnTarget": 3,
    "cleanSheets": 8,
    "yellowCards": 7,
    "redCards": 0
  },
  {
    "id": 162,
    "name": "Youssef En-Nesyri",
    "team": "Arsenal",
    "league": "Premier League",
    "position": "Defender",
    "age": 25,
    "minutesPlayed": 2011,
    "goals": 1,
    "assists": 1,
    "rating": 6.6,
    "passes": 1303,
    "tackles": 126,
    "interceptions": 32,
    "dribbles": 19,
    "keyPasses": 18,
    "shots": 20,
    "shotsOnTarget": 6,
    "cleanSheets": 17,
    "yellowCards": 3,
    "redCards": 0
  },
  {
    "id": 163,
    "name": "Andre Onana",
    "team": "Liverpool",
    "league": "Premier League",
    "position": "Defender",
    "age": 27,
    "minutesPlayed": 2951,
    "goals": 4,
    "assists": 2,
    "rating": 7,
    "passes": 660,
    "tackles": 46,
    "interceptions": 61,
    "dribbles": 23,
    "keyPasses": 11,
    "shots": 21,
    "shotsOnTarget": 6,
    "cleanSheets": 5,
    "yellowCards": 7,
    "redCards": 2
  },
  {
    "id": 164,
    "name": "Darwin Nunez",
    "team": "Chelsea",
    "league": "Premier League",
    "position": "Defender",
    "age": 20,
    "minutesPlayed": 1673,
    "goals": 0,
    "assists": 3,
    "rating": 6.3,
    "passes": 670,
    "tackles": 109,
    "interceptions": 68,
    "dribbles": 9,
    "keyPasses": 9,
    "shots": 22,
    "shotsOnTarget": 6,
    "cleanSheets": 18,
    "yellowCards": 6,
    "redCards": 0
  },
  {
    "id": 165,
    "name": "Luis Diaz",
    "team": "Real Madrid",
    "league": "La Liga",
    "position": "Defender",
    "age": 30,
    "minutesPlayed": 2683,
    "goals": 0,
    "assists": 2,
    "rating": 6.5,
    "passes": 1834,
    "tackles": 88,
    "interceptions": 94,
    "dribbles": 14,
    "keyPasses": 23,
    "shots": 12,
    "shotsOnTarget": 4,
    "cleanSheets": 10,
    "yellowCards": 5,
    "redCards": 1
  },
  {
    "id": 166,
    "name": "Angel Di Maria",
    "team": "Barcelona",
    "league": "La Liga",
    "position": "Defender",
    "age": 22,
    "minutesPlayed": 1934,
    "goals": 5,
    "assists": 6,
    "rating": 7.2,
    "passes": 1760,
    "tackles": 81,
    "interceptions": 31,
    "dribbles": 25,
    "keyPasses": 23,
    "shots": 12,
    "shotsOnTarget": 2,
    "cleanSheets": 10,
    "yellowCards": 9,
    "redCards": 2
  },
  {
    "id": 167,
    "name": "Cristian Romero",
    "team": "Atletico Madrid",
    "league": "La Liga",
    "position": "Defender",
    "age": 30,
    "minutesPlayed": 2775,
    "goals": 3,
    "assists": 7,
    "rating": 6.4,
    "passes": 1678,
    "tackles": 47,
    "interceptions": 62,
    "dribbles": 26,
    "keyPasses": 12,
    "shots": 8,
    "shotsOnTarget": 3,
    "cleanSheets": 8,
    "yellowCards": 9,
    "redCards": 2
  },
  {
    "id": 168,
    "name": "Eduardo Camavinga",
    "team": "Bayern Munich",
    "league": "Bundesliga",
    "position": "Defender",
    "age": 24,
    "minutesPlayed": 2748,
    "goals": 5,
    "assists": 4,
    "rating": 7.4,
    "passes": 1565,
    "tackles": 84,
    "interceptions": 83,
    "dribbles": 23,
    "keyPasses": 22,
    "shots": 16,
    "shotsOnTarget": 3,
    "cleanSheets": 15,
    "yellowCards": 8,
    "redCards": 1
  },
  {
    "id": 169,
    "name": "Mateo Kovacic",
    "team": "Borussia Dortmund",
    "league": "Bundesliga",
    "position": "Defender",
    "age": 31,
    "minutesPlayed": 2146,
    "goals": 1,
    "assists": 4,
    "rating": 7.7,
    "passes": 1613,
    "tackles": 93,
    "interceptions": 43,
    "dribbles": 19,
    "keyPasses": 11,
    "shots": 11,
    "shotsOnTarget": 3,
    "cleanSheets": 11,
    "yellowCards": 11,
    "redCards": 1
  },
  {
    "id": 170,
    "name": "Nicolas Perez",
    "team": "RB Leipzig",
    "league": "Bundesliga",
    "position": "Defender",
    "age": 30,
    "minutesPlayed": 1168,
    "goals": 3,
    "assists": 2,
    "rating": 6.5,
    "passes": 1167,
    "tackles": 112,
    "interceptions": 67,
    "dribbles": 26,
    "keyPasses": 10,
    "shots": 20,
    "shotsOnTarget": 8,
    "cleanSheets": 16,
    "yellowCards": 10,
    "redCards": 0
  },
  {
    "id": 171,
    "name": "Santiago Valverde",
    "team": "Juventus",
    "league": "Serie A",
    "position": "Goalkeeper",
    "age": 26,
    "minutesPlayed": 2949,
    "goals": 0,
    "assists": 0,
    "rating": 7.5,
    "passes": 363,
    "tackles": 0,
    "interceptions": 1,
    "dribbles": 1,
    "keyPasses": 1,
    "shots": 0,
    "shotsOnTarget": 0,
    "cleanSheets": 6,
    "yellowCards": 2,
    "redCards": 0
  },
  {
    "id": 172,
    "name": "Diego Costa",
    "team": "AC Milan",
    "league": "Serie A",
    "position": "Goalkeeper",
    "age": 32,
    "minutesPlayed": 2098,
    "goals": 0,
    "assists": 2,
    "rating": 6.6,
    "passes": 801,
    "tackles": 1,
    "interceptions": 3,
    "dribbles": 3,
    "keyPasses": 4,
    "shots": 0,
    "shotsOnTarget": 0,
    "cleanSheets": 18,
    "yellowCards": 1,
    "redCards": 1
  },
  {
    "id": 173,
    "name": "Alvaro Morata",
    "team": "Inter Milan",
    "league": "Serie A",
    "position": "Goalkeeper",
    "age": 25,
    "minutesPlayed": 2038,
    "goals": 0,
    "assists": 1,
    "rating": 6.5,
    "passes": 332,
    "tackles": 4,
    "interceptions": 7,
    "dribbles": 3,
    "keyPasses": 0,
    "shots": 0,
    "shotsOnTarget": 0,
    "cleanSheets": 11,
    "yellowCards": 2,
    "redCards": 1
  },
  {
    "id": 174,
    "name": "Isco Alarcon",
    "team": "Napoli",
    "league": "Serie A",
    "position": "Goalkeeper",
    "age": 23,
    "minutesPlayed": 2407,
    "goals": 0,
    "assists": 1,
    "rating": 6.8,
    "passes": 432,
    "tackles": 1,
    "interceptions": 8,
    "dribbles": 1,
    "keyPasses": 0,
    "shots": 0,
    "shotsOnTarget": 0,
    "cleanSheets": 12,
    "yellowCards": 4,
    "redCards": 1
  },
  {
    "id": 175,
    "name": "Dani Carvajal",
    "team": "Paris Saint-Germain",
    "league": "Ligue 1",
    "position": "Goalkeeper",
    "age": 36,
    "minutesPlayed": 2265,
    "goals": 0,
    "assists": 1,
    "rating": 6.4,
    "passes": 811,
    "tackles": 3,
    "interceptions": 1,
    "dribbles": 1,
    "keyPasses": 3,
    "shots": 0,
    "shotsOnTarget": 0,
    "cleanSheets": 20,
    "yellowCards": 4,
    "redCards": 0
  },
  {
    "id": 176,
    "name": "Marcos Llorente",
    "team": "AS Monaco",
    "league": "Ligue 1",
    "position": "Goalkeeper",
    "age": 26,
    "minutesPlayed": 1030,
    "goals": 0,
    "assists": 1,
    "rating": 6.8,
    "passes": 312,
    "tackles": 3,
    "interceptions": 10,
    "dribbles": 0,
    "keyPasses": 1,
    "shots": 0,
    "shotsOnTarget": 0,
    "cleanSheets": 6,
    "yellowCards": 0,
    "redCards": 0
  },
  {
    "id": 177,
    "name": "Aymeric Laporte",
    "team": "Benfica",
    "league": "Primeira Liga",
    "position": "Goalkeeper",
    "age": 28,
    "minutesPlayed": 2135,
    "goals": 0,
    "assists": 1,
    "rating": 7.2,
    "passes": 303,
    "tackles": 1,
    "interceptions": 4,
    "dribbles": 1,
    "keyPasses": 0,
    "shots": 0,
    "shotsOnTarget": 0,
    "cleanSheets": 16,
    "yellowCards": 4,
    "redCards": 0
  },
  {
    "id": 178,
    "name": "Josko Gvardiol",
    "team": "Porto",
    "league": "Primeira Liga",
    "position": "Goalkeeper",
    "age": 22,
    "minutesPlayed": 1002,
    "goals": 0,
    "assists": 0,
    "rating": 6.2,
    "passes": 457,
    "tackles": 1,
    "interceptions": 5,
    "dribbles": 1,
    "keyPasses": 5,
    "shots": 0,
    "shotsOnTarget": 0,
    "cleanSheets": 16,
    "yellowCards": 2,
    "redCards": 1
  },
  {
    "id": 179,
    "name": "Dominic Calvert-Lewin",
    "team": "Ajax",
    "league": "Eredivisie",
    "position": "Goalkeeper",
    "age": 22,
    "minutesPlayed": 1774,
    "goals": 0,
    "assists": 1,
    "rating": 6.2,
    "passes": 531,
    "tackles": 4,
    "interceptions": 3,
    "dribbles": 3,
    "keyPasses": 5,
    "shots": 0,
    "shotsOnTarget": 0,
    "cleanSheets": 12,
    "yellowCards": 0,
    "redCards": 0
  },
  {
    "id": 180,
    "name": "Tammy Abraham",
    "team": "Galatasaray",
    "league": "Super Lig",
    "position": "Goalkeeper",
    "age": 20,
    "minutesPlayed": 1670,
    "goals": 0,
    "assists": 2,
    "rating": 6.5,
    "passes": 761,
    "tackles": 1,
    "interceptions": 7,
    "dribbles": 3,
    "keyPasses": 2,
    "shots": 0,
    "shotsOnTarget": 0,
    "cleanSheets": 4,
    "yellowCards": 3,
    "redCards": 1
  },
  {
    "id": 181,
    "name": "Callum Wilson",
    "team": "Manchester City",
    "league": "Premier League",
    "position": "Goalkeeper",
    "age": 20,
    "minutesPlayed": 2838,
    "goals": 0,
    "assists": 0,
    "rating": 7.6,
    "passes": 595,
    "tackles": 5,
    "interceptions": 3,
    "dribbles": 2,
    "keyPasses": 0,
    "shots": 0,
    "shotsOnTarget": 0,
    "cleanSheets": 16,
    "yellowCards": 2,
    "redCards": 0
  },
  {
    "id": 182,
    "name": "Reece James",
    "team": "Arsenal",
    "league": "Premier League",
    "position": "Goalkeeper",
    "age": 24,
    "minutesPlayed": 1177,
    "goals": 0,
    "assists": 1,
    "rating": 6.5,
    "passes": 877,
    "tackles": 5,
    "interceptions": 5,
    "dribbles": 0,
    "keyPasses": 5,
    "shots": 0,
    "shotsOnTarget": 0,
    "cleanSheets": 14,
    "yellowCards": 0,
    "redCards": 1
  },
  {
    "id": 183,
    "name": "Ben Chilwell",
    "team": "Liverpool",
    "league": "Premier League",
    "position": "Goalkeeper",
    "age": 34,
    "minutesPlayed": 1930,
    "goals": 0,
    "assists": 2,
    "rating": 7.1,
    "passes": 633,
    "tackles": 4,
    "interceptions": 7,
    "dribbles": 0,
    "keyPasses": 5,
    "shots": 0,
    "shotsOnTarget": 0,
    "cleanSheets": 13,
    "yellowCards": 2,
    "redCards": 0
  },
  {
    "id": 184,
    "name": "Trent Alexander-Arnold",
    "team": "Chelsea",
    "league": "Premier League",
    "position": "Goalkeeper",
    "age": 22,
    "minutesPlayed": 1469,
    "goals": 0,
    "assists": 2,
    "rating": 6.1,
    "passes": 381,
    "tackles": 4,
    "interceptions": 5,
    "dribbles": 2,
    "keyPasses": 5,
    "shots": 0,
    "shotsOnTarget": 0,
    "cleanSheets": 15,
    "yellowCards": 1,
    "redCards": 1
  },
  {
    "id": 185,
    "name": "Andrew Robertson",
    "team": "Real Madrid",
    "league": "La Liga",
    "position": "Goalkeeper",
    "age": 29,
    "minutesPlayed": 1974,
    "goals": 0,
    "assists": 2,
    "rating": 7.2,
    "passes": 787,
    "tackles": 5,
    "interceptions": 6,
    "dribbles": 0,
    "keyPasses": 0,
    "shots": 0,
    "shotsOnTarget": 0,
    "cleanSheets": 5,
    "yellowCards": 2,
    "redCards": 0
  },
  {
    "id": 186,
    "name": "Mason Mount",
    "team": "Barcelona",
    "league": "La Liga",
    "position": "Goalkeeper",
    "age": 24,
    "minutesPlayed": 1593,
    "goals": 0,
    "assists": 0,
    "rating": 6.3,
    "passes": 550,
    "tackles": 0,
    "interceptions": 4,
    "dribbles": 3,
    "keyPasses": 5,
    "shots": 0,
    "shotsOnTarget": 0,
    "cleanSheets": 17,
    "yellowCards": 1,
    "redCards": 1
  },
  {
    "id": 187,
    "name": "Jack Grealish",
    "team": "Atletico Madrid",
    "league": "La Liga",
    "position": "Goalkeeper",
    "age": 27,
    "minutesPlayed": 617,
    "goals": 0,
    "assists": 2,
    "rating": 7.8,
    "passes": 525,
    "tackles": 4,
    "interceptions": 10,
    "dribbles": 1,
    "keyPasses": 3,
    "shots": 0,
    "shotsOnTarget": 0,
    "cleanSheets": 4,
    "yellowCards": 3,
    "redCards": 0
  },
  {
    "id": 188,
    "name": "Emile Smith Rowe",
    "team": "Bayern Munich",
    "league": "Bundesliga",
    "position": "Goalkeeper",
    "age": 25,
    "minutesPlayed": 1970,
    "goals": 0,
    "assists": 2,
    "rating": 6.6,
    "passes": 779,
    "tackles": 1,
    "interceptions": 8,
    "dribbles": 2,
    "keyPasses": 5,
    "shots": 0,
    "shotsOnTarget": 0,
    "cleanSheets": 9,
    "yellowCards": 3,
    "redCards": 0
  },
  {
    "id": 189,
    "name": "Kieran Trippier",
    "team": "Borussia Dortmund",
    "league": "Bundesliga",
    "position": "Goalkeeper",
    "age": 21,
    "minutesPlayed": 2950,
    "goals": 0,
    "assists": 0,
    "rating": 7.7,
    "passes": 691,
    "tackles": 1,
    "interceptions": 4,
    "dribbles": 2,
    "keyPasses": 0,
    "shots": 0,
    "shotsOnTarget": 0,
    "cleanSheets": 6,
    "yellowCards": 3,
    "redCards": 0
  },
  {
    "id": 190,
    "name": "Aaron Ramsdale",
    "team": "RB Leipzig",
    "league": "Bundesliga",
    "position": "Goalkeeper",
    "age": 29,
    "minutesPlayed": 1471,
    "goals": 0,
    "assists": 2,
    "rating": 6.6,
    "passes": 358,
    "tackles": 5,
    "interceptions": 4,
    "dribbles": 0,
    "keyPasses": 4,
    "shots": 0,
    "shotsOnTarget": 0,
    "cleanSheets": 20,
    "yellowCards": 4,
    "redCards": 0
  },
  {
    "id": 191,
    "name": "William Saliba",
    "team": "Juventus",
    "league": "Serie A",
    "position": "Goalkeeper",
    "age": 29,
    "minutesPlayed": 1982,
    "goals": 0,
    "assists": 1,
    "rating": 7.1,
    "passes": 480,
    "tackles": 3,
    "interceptions": 9,
    "dribbles": 3,
    "keyPasses": 5,
    "shots": 0,
    "shotsOnTarget": 0,
    "cleanSheets": 5,
    "yellowCards": 0,
    "redCards": 0
  },
  {
    "id": 192,
    "name": "Pierre Aubameyang",
    "team": "AC Milan",
    "league": "Serie A",
    "position": "Goalkeeper",
    "age": 34,
    "minutesPlayed": 755,
    "goals": 0,
    "assists": 0,
    "rating": 6.1,
    "passes": 687,
    "tackles": 5,
    "interceptions": 3,
    "dribbles": 2,
    "keyPasses": 1,
    "shots": 0,
    "shotsOnTarget": 0,
    "cleanSheets": 7,
    "yellowCards": 4,
    "redCards": 1
  },
  {
    "id": 193,
    "name": "Alexandre Lacazette",
    "team": "Inter Milan",
    "league": "Serie A",
    "position": "Goalkeeper",
    "age": 27,
    "minutesPlayed": 893,
    "goals": 0,
    "assists": 0,
    "rating": 7.3,
    "passes": 318,
    "tackles": 0,
    "interceptions": 3,
    "dribbles": 3,
    "keyPasses": 4,
    "shots": 0,
    "shotsOnTarget": 0,
    "cleanSheets": 11,
    "yellowCards": 2,
    "redCards": 0
  },
  {
    "id": 194,
    "name": "Youri Tielemans",
    "team": "Napoli",
    "league": "Serie A",
    "position": "Goalkeeper",
    "age": 34,
    "minutesPlayed": 2455,
    "goals": 0,
    "assists": 2,
    "rating": 6.1,
    "passes": 689,
    "tackles": 0,
    "interceptions": 8,
    "dribbles": 2,
    "keyPasses": 4,
    "shots": 0,
    "shotsOnTarget": 0,
    "cleanSheets": 12,
    "yellowCards": 1,
    "redCards": 0
  },
  {
    "id": 195,
    "name": "Alexis Sanchez",
    "team": "Paris Saint-Germain",
    "league": "Ligue 1",
    "position": "Goalkeeper",
    "age": 30,
    "minutesPlayed": 2338,
    "goals": 0,
    "assists": 1,
    "rating": 7.7,
    "passes": 883,
    "tackles": 4,
    "interceptions": 1,
    "dribbles": 3,
    "keyPasses": 5,
    "shots": 0,
    "shotsOnTarget": 0,
    "cleanSheets": 13,
    "yellowCards": 1,
    "redCards": 1
  },
  {
    "id": 196,
    "name": "Ferran Torres",
    "team": "AS Monaco",
    "league": "Ligue 1",
    "position": "Goalkeeper",
    "age": 23,
    "minutesPlayed": 670,
    "goals": 0,
    "assists": 2,
    "rating": 6.1,
    "passes": 417,
    "tackles": 5,
    "interceptions": 8,
    "dribbles": 0,
    "keyPasses": 0,
    "shots": 0,
    "shotsOnTarget": 0,
    "cleanSheets": 19,
    "yellowCards": 3,
    "redCards": 0
  },
  {
    "id": 197,
    "name": "Ansu Fati",
    "team": "Benfica",
    "league": "Primeira Liga",
    "position": "Goalkeeper",
    "age": 25,
    "minutesPlayed": 2579,
    "goals": 0,
    "assists": 1,
    "rating": 7.6,
    "passes": 814,
    "tackles": 4,
    "interceptions": 3,
    "dribbles": 3,
    "keyPasses": 2,
    "shots": 0,
    "shotsOnTarget": 0,
    "cleanSheets": 6,
    "yellowCards": 2,
    "redCards": 1
  },
  {
    "id": 198,
    "name": "Ronald Araujo",
    "team": "Porto",
    "league": "Primeira Liga",
    "position": "Goalkeeper",
    "age": 30,
    "minutesPlayed": 2003,
    "goals": 0,
    "assists": 2,
    "rating": 6.2,
    "passes": 318,
    "tackles": 2,
    "interceptions": 9,
    "dribbles": 2,
    "keyPasses": 4,
    "shots": 0,
    "shotsOnTarget": 0,
    "cleanSheets": 9,
    "yellowCards": 2,
    "redCards": 1
  },
  {
    "id": 199,
    "name": "Fede Valverde",
    "team": "Ajax",
    "league": "Eredivisie",
    "position": "Goalkeeper",
    "age": 31,
    "minutesPlayed": 1487,
    "goals": 0,
    "assists": 1,
    "rating": 6.3,
    "passes": 772,
    "tackles": 0,
    "interceptions": 3,
    "dribbles": 0,
    "keyPasses": 3,
    "shots": 0,
    "shotsOnTarget": 0,
    "cleanSheets": 20,
    "yellowCards": 0,
    "redCards": 1
  },
  {
    "id": 200,
    "name": "Toni Kroos",
    "team": "Galatasaray",
    "league": "Super Lig",
    "position": "Goalkeeper",
    "age": 19,
    "minutesPlayed": 1527,
    "goals": 0,
    "assists": 1,
    "rating": 7.5,
    "passes": 842,
    "tackles": 5,
    "interceptions": 7,
    "dribbles": 0,
    "keyPasses": 0,
    "shots": 0,
    "shotsOnTarget": 0,
    "cleanSheets": 15,
    "yellowCards": 4,
    "redCards": 0
  }
]